<?xml version="1.0" encoding="UTF-8"?>
<!--Copyright 2024 The MathWorks, Inc.-->

<rsccat xmlns:xsi="http://www.w3.org/2001/XMLSchema-instance" version="1.0" locale="zh_CN" product="mlreportgen" xsi:noNamespaceSchemaLocation="../../resources/schema/msgcat.xsd">
  <message>
    <entry key="invalidInputPath">Invalid input path: "{0}".</entry>
    <entry key="invalidStylesheetPath">Invalid stylesheet path: "{0}".</entry>
    <entry key="invalidOutputPath">Invalid output path: "{0}".</entry>
    <entry key="parserCtxtError">无法为输入解析器创建上下文。</entry>
    <entry key="inputParseError">无法解析输入文件: "{0}"。\n原因: {1}。</entry>
    <entry key="ssParseFileError">Unable to parse stylesheet file: "{0}".\n  Reason: {1}.</entry>
    <entry key="ssParseDocError">Unable to parse stylesheet document: "{0}".</entry>
    <entry key="xfrmError">无法转换输入文件: "{0}"。\n原因: {1}。</entry>
    <entry key="xfrmOutputError">Unable to write transform result to output file: "{0}".</entry>
    <entry key="xfrmInternalError">Internal error occurred transforming input file: "{0}".</entry>
    <entry key="xfrmPathLengthError">File path length ({0,number,integer}) exceeds Windows path length limit (259 characters).\n Invalid path: {1}.</entry>
    <entry key="externalResourceError">Failed to load external entity: "{0}".</entry>
    <entry key="externalEntityPathLengthError">外部实体文件路径长度({0,number,integer})超出 Windows 路径长度限制(259 个字符)。\n无效路径: {1}。</entry>
    <entry key="remoteResourceError">Loading remote resource not allowed. Remote resource: "{0}".</entry>
  </message>
</rsccat>
