<?xml version="1.0" encoding="UTF-8"?>
<!--Copyright 2024 The MathWorks, Inc.-->

<rsccat xmlns:xsi="http://www.w3.org/2001/XMLSchema-instance" version="1.0" locale="zh_CN" product="coderapp_shared_screener" xsi:noNamespaceSchemaLocation="../../resources/schema/msgcat.xsd">
  <message>
    <entry key="EMBRK">HDL 代码生成不支持 break 语句。</entry>
    <entry key="EMCEL">定点转换不支持元胞数组。</entry>
    <entry key="EMCNT">HDL 代码生成不支持 continue 语句。</entry>
    <entry key="EMNST">定点转换不支持嵌套函数。</entry>
    <entry key="EMPFR">HDL 代码生成不支持 parfor 语句。</entry>
    <entry key="EMSCR">代码生成不支持脚本。</entry>
    <entry key="EMWHL">HDL 代码生成不支持 while 语句。</entry>
    <entry key="EMTC">代码生成不支持 TRY/CATCH。</entry>
    <entry key="EMIMP">代码生成不支持 import 语句。</entry>
    <entry key="EMRTN">HDL 代码生成不支持循环内部的 return 语句。</entry>
    <entry key="EMRIFAV">代码生成不支持带验证的重复参数。</entry>
    <entry key="EMRIFAVX">代码生成不支持多个重复的输入参数。</entry>
    <entry key="EMS2N">代码生成不支持 'str2num'。请改用 'str2double'。</entry>
    <entry key="LOOPPRAGMAWITHOUTFOR">coder.loop.Control 变换后面必须紧跟 for 循环。</entry>
    <entry key="EMLOAD">调用 LOAD 产生的输出未赋给变量。对于代码生成，将 LOAD 的输出赋给变量而不加下标。</entry>
  </message>
</rsccat>
