{
    "aiofiles.threadpool.utils.delegate_to_executor": [],
    "aiofiles.threadpool.utils.proxy_method_directly": [],
    "aiofiles.threadpool.utils.proxy_property_directly": [],
    "aiofiles.threadpool.utils.cond_delegate_to_executor": [],
    "aiofiles.threadpool.binary._UnknownAsyncBinaryIO.fileno": [
        ""
    ],
    "aiofiles.threadpool.binary._UnknownAsyncBinaryIO.readable": [
        ""
    ],
    "aiofiles.threadpool.binary._UnknownAsyncBinaryIO.closed": [
        ""
    ],
    "aiofiles.threadpool.binary._UnknownAsyncBinaryIO.mode": [
        ""
    ],
    "aiofiles.threadpool.binary._UnknownAsyncBinaryIO.name": [
        ""
    ],
    "aiofiles.threadpool.binary.AsyncBufferedIOBase.detach": [
        ""
    ],
    "aiofiles.threadpool.binary.AsyncBufferedIOBase.raw": [
        ""
    ],
    "aiofiles.threadpool.binary.AsyncIndirectBufferedIOBase.detach": [
        ""
    ],
    "aiofiles.threadpool.binary.AsyncIndirectBufferedIOBase.raw": [
        ""
    ],
    "aiofiles.threadpool.__init__.open": [
        "FileDescriptorOrPath",
        "OpenTextMode",
        "int",
        "str | None",
        "str | None",
        "str | None",
        "bool",
        "_Opener | None"
    ],
    "aiofiles.threadpool.text._UnknownAsyncTextIO.detach": [
        ""
    ],
    "aiofiles.threadpool.text._UnknownAsyncTextIO.fileno": [
        ""
    ],
    "aiofiles.threadpool.text._UnknownAsyncTextIO.readable": [
        ""
    ],
    "aiofiles.threadpool.text._UnknownAsyncTextIO.buffer": [
        ""
    ],
    "aiofiles.threadpool.text._UnknownAsyncTextIO.closed": [
        ""
    ],
    "aiofiles.threadpool.text._UnknownAsyncTextIO.encoding": [
        ""
    ],
    "aiofiles.threadpool.text._UnknownAsyncTextIO.errors": [
        ""
    ],
    "aiofiles.threadpool.text._UnknownAsyncTextIO.line_buffering": [
        ""
    ],
    "aiofiles.threadpool.text._UnknownAsyncTextIO.newlines": [
        ""
    ],
    "aiofiles.threadpool.text._UnknownAsyncTextIO.name": [
        ""
    ],
    "aiofiles.threadpool.text._UnknownAsyncTextIO.mode": [
        ""
    ],
    "aiofiles.tempfile.__init__.NamedTemporaryFile": [
        "OpenTextMode",
        "int",
        "str | None",
        "str | None",
        "AnyStr | None",
        "AnyStr | None",
        "StrOrBytesPath | None",
        "bool",
        "AbstractEventLoop | None",
        "Incomplete | None"
    ],
    "aiofiles.tempfile.__init__.TemporaryFile": [
        "OpenTextMode",
        "int",
        "str | None",
        "str | None",
        "AnyStr | None",
        "AnyStr | None",
        "StrOrBytesPath | None",
        "AbstractEventLoop | None",
        "Incomplete | None"
    ],
    "aiofiles.tempfile.__init__.SpooledTemporaryFile": [
        "int"
    ],
    "aiofiles.tempfile.__init__.TemporaryDirectory": [
        "str | None",
        "str | None",
        "StrPath | None",
        "AbstractEventLoop | None",
        "Incomplete | None"
    ],
    "aiofiles.tempfile.temptypes.AsyncSpooledTemporaryFile.fileno": [
        ""
    ],
    "aiofiles.tempfile.temptypes.AsyncSpooledTemporaryFile.rollover": [
        ""
    ],
    "aiofiles.tempfile.temptypes.AsyncSpooledTemporaryFile.closed": [
        ""
    ],
    "aiofiles.tempfile.temptypes.AsyncSpooledTemporaryFile.encoding": [
        ""
    ],
    "aiofiles.tempfile.temptypes.AsyncSpooledTemporaryFile.mode": [
        ""
    ],
    "aiofiles.tempfile.temptypes.AsyncSpooledTemporaryFile.name": [
        ""
    ],
    "aiofiles.tempfile.temptypes.AsyncSpooledTemporaryFile.newlines": [
        ""
    ],
    "aiofiles.tempfile.temptypes.AsyncTemporaryDirectory.name": [
        ""
    ],
    "aiofiles.tempfile.temptypes.AsyncTemporaryDirectory.__init__": [
        "",
        "TemporaryDirectory[Incomplete]",
        "AbstractEventLoop | None",
        "Incomplete | None"
    ],
    "aiofiles.base.AsyncBase.__init__": [
        "",
        "str",
        "Any",
        "Any"
    ],
    "aiofiles.base.AsyncBase.__aiter__": [
        ""
    ],
    "aiofiles.base.AsyncIndirectBase.__init__": [
        "",
        "str",
        "Any",
        "Any",
        "Callable[[], TextIO | BinaryIO]"
    ],
    "aiofiles.base.AiofilesContextManager.__init__": [
        "",
        "Coroutine[_T_co, _T_contra, _V_co]"
    ],
    "aiofiles.base.AiofilesContextManager.send": [
        "",
        "_T_contra"
    ],
    "aiofiles.base.AiofilesContextManager.throw": [
        "",
        "type[BaseException]",
        "BaseException | object",
        "TracebackType | None"
    ],
    "aiofiles.base.AiofilesContextManager.close": [
        ""
    ],
    "aiofiles.base.AiofilesContextManager.gi_frame": [
        ""
    ],
    "aiofiles.base.AiofilesContextManager.gi_running": [
        ""
    ],
    "aiofiles.base.AiofilesContextManager.gi_code": [
        ""
    ],
    "aiofiles.base.AiofilesContextManager.__next__": [
        ""
    ],
    "aiofiles.base.AiofilesContextManager.__iter__": [
        ""
    ],
    "aiofiles.base.AiofilesContextManager.__await__": [
        ""
    ]
}