{
    "calendar.IllegalMonthError.__init__": [
        "",
        "int"
    ],
    "calendar.IllegalWeekdayError.__init__": [
        "",
        "int"
    ],
    "calendar.Calendar.__init__": [
        "",
        "int"
    ],
    "calendar.Calendar.getfirstweekday": [
        ""
    ],
    "calendar.Calendar.setfirstweekday": [
        "",
        "int"
    ],
    "calendar.Calendar.iterweekdays": [
        ""
    ],
    "calendar.Calendar.itermonthdates": [
        "",
        "int",
        "int"
    ],
    "calendar.Calendar.itermonthdays2": [
        "",
        "int",
        "int"
    ],
    "calendar.Calendar.itermonthdays": [
        "",
        "int",
        "int"
    ],
    "calendar.Calendar.monthdatescalendar": [
        "",
        "int",
        "int"
    ],
    "calendar.Calendar.monthdays2calendar": [
        "",
        "int",
        "int"
    ],
    "calendar.Calendar.monthdayscalendar": [
        "",
        "int",
        "int"
    ],
    "calendar.Calendar.yeardatescalendar": [
        "",
        "int",
        "int"
    ],
    "calendar.Calendar.yeardays2calendar": [
        "",
        "int",
        "int"
    ],
    "calendar.Calendar.yeardayscalendar": [
        "",
        "int",
        "int"
    ],
    "calendar.Calendar.itermonthdays3": [
        "",
        "int",
        "int"
    ],
    "calendar.Calendar.itermonthdays4": [
        "",
        "int",
        "int"
    ],
    "calendar.TextCalendar.prweek": [
        "",
        "int",
        "int"
    ],
    "calendar.TextCalendar.formatday": [
        "",
        "int",
        "int",
        "int"
    ],
    "calendar.TextCalendar.formatweek": [
        "",
        "int",
        "int"
    ],
    "calendar.TextCalendar.formatweekday": [
        "",
        "int",
        "int"
    ],
    "calendar.TextCalendar.formatweekheader": [
        "",
        "int"
    ],
    "calendar.TextCalendar.formatmonthname": [
        "",
        "int",
        "int",
        "int",
        "bool"
    ],
    "calendar.TextCalendar.prmonth": [
        "",
        "int",
        "int",
        "int",
        "int"
    ],
    "calendar.TextCalendar.formatmonth": [
        "",
        "int",
        "int",
        "int",
        "int"
    ],
    "calendar.TextCalendar.formatyear": [
        "",
        "int",
        "int",
        "int",
        "int",
        "int"
    ],
    "calendar.TextCalendar.pryear": [
        "",
        "int",
        "int",
        "int",
        "int",
        "int"
    ],
    "calendar.HTMLCalendar.formatday": [
        "",
        "int",
        "int"
    ],
    "calendar.HTMLCalendar.formatweek": [
        "",
        "int"
    ],
    "calendar.HTMLCalendar.formatweekday": [
        "",
        "int"
    ],
    "calendar.HTMLCalendar.formatweekheader": [
        ""
    ],
    "calendar.HTMLCalendar.formatmonthname": [
        "",
        "int",
        "int",
        "bool"
    ],
    "calendar.HTMLCalendar.formatmonth": [
        "",
        "int",
        "int",
        "bool"
    ],
    "calendar.HTMLCalendar.formatyear": [
        "",
        "int",
        "int"
    ],
    "calendar.HTMLCalendar.formatyearpage": [
        "",
        "int",
        "int",
        "str | None",
        "str | None"
    ],
    "calendar.different_locale.__init__": [
        "",
        "_LocaleType"
    ],
    "calendar.different_locale.__enter__": [
        ""
    ],
    "calendar.different_locale.__exit__": [
        ""
    ],
    "calendar.LocaleTextCalendar.__init__": [
        "",
        "int",
        "_LocaleType | None"
    ],
    "calendar.LocaleHTMLCalendar.__init__": [
        "",
        "int",
        "_LocaleType | None"
    ],
    "calendar.LocaleHTMLCalendar.formatweekday": [
        "",
        "int"
    ],
    "calendar.LocaleHTMLCalendar.formatmonthname": [
        "",
        "int",
        "int",
        "bool"
    ],
    "calendar.isleap": [
        "int"
    ],
    "calendar.leapdays": [
        "int",
        "int"
    ],
    "calendar.weekday": [
        "int",
        "int",
        "int"
    ],
    "calendar.monthrange": [
        "int",
        "int"
    ],
    "calendar.firstweekday": [],
    "calendar.monthcalendar": [
        "int",
        "int"
    ],
    "calendar.prweek": [
        "int",
        "int"
    ],
    "calendar.week": [
        "int",
        "int"
    ],
    "calendar.weekheader": [
        "int"
    ],
    "calendar.prmonth": [
        "int",
        "int",
        "int",
        "int"
    ],
    "calendar.month": [
        "int",
        "int",
        "int",
        "int"
    ],
    "calendar.calendar": [
        "int",
        "int",
        "int",
        "int",
        "int"
    ],
    "calendar.prcal": [
        "int",
        "int",
        "int",
        "int",
        "int"
    ],
    "calendar.setfirstweekday": [
        "int"
    ],
    "calendar.format": [
        "int",
        "int",
        "int"
    ],
    "calendar.formatstring": [
        "int",
        "int",
        "int"
    ],
    "calendar.timegm": [
        "tuple[int, ...] | struct_time"
    ]
}