{
    "pathlib.PurePath.parts": [
        ""
    ],
    "pathlib.PurePath.drive": [
        ""
    ],
    "pathlib.PurePath.root": [
        ""
    ],
    "pathlib.PurePath.anchor": [
        ""
    ],
    "pathlib.PurePath.name": [
        ""
    ],
    "pathlib.PurePath.suffix": [
        ""
    ],
    "pathlib.PurePath.suffixes": [
        ""
    ],
    "pathlib.PurePath.stem": [
        ""
    ],
    "pathlib.PurePath.__new__": [
        ""
    ],
    "pathlib.PurePath.__hash__": [
        ""
    ],
    "pathlib.PurePath.__eq__": [
        "",
        "object"
    ],
    "pathlib.PurePath.__fspath__": [
        ""
    ],
    "pathlib.PurePath.__lt__": [
        "",
        "PurePath"
    ],
    "pathlib.PurePath.__le__": [
        "",
        "PurePath"
    ],
    "pathlib.PurePath.__gt__": [
        "",
        "PurePath"
    ],
    "pathlib.PurePath.__ge__": [
        "",
        "PurePath"
    ],
    "pathlib.PurePath.__truediv__": [
        "",
        "StrPath"
    ],
    "pathlib.PurePath.__rtruediv__": [
        "",
        "StrPath"
    ],
    "pathlib.PurePath.__bytes__": [
        ""
    ],
    "pathlib.PurePath.as_posix": [
        ""
    ],
    "pathlib.PurePath.as_uri": [
        ""
    ],
    "pathlib.PurePath.is_absolute": [
        ""
    ],
    "pathlib.PurePath.is_reserved": [
        ""
    ],
    "pathlib.PurePath.relative_to": [
        ""
    ],
    "pathlib.PurePath.with_name": [
        "",
        "str"
    ],
    "pathlib.PurePath.with_suffix": [
        "",
        "str"
    ],
    "pathlib.PurePath.joinpath": [
        ""
    ],
    "pathlib.PurePath.parents": [
        ""
    ],
    "pathlib.PurePath.parent": [
        ""
    ],
    "pathlib.Path.__new__": [
        ""
    ],
    "pathlib.Path.__enter__": [
        ""
    ],
    "pathlib.Path.__exit__": [
        "",
        "type[BaseException] | None",
        "BaseException | None",
        "TracebackType | None"
    ],
    "pathlib.Path.cwd": [
        ""
    ],
    "pathlib.Path.is_dir": [
        ""
    ],
    "pathlib.Path.is_file": [
        ""
    ],
    "pathlib.Path.is_symlink": [
        ""
    ],
    "pathlib.Path.is_socket": [
        ""
    ],
    "pathlib.Path.is_fifo": [
        ""
    ],
    "pathlib.Path.is_block_device": [
        ""
    ],
    "pathlib.Path.is_char_device": [
        ""
    ],
    "pathlib.Path.iterdir": [
        ""
    ],
    "pathlib.Path.lchmod": [
        "",
        "int"
    ],
    "pathlib.Path.lstat": [
        ""
    ],
    "pathlib.Path.mkdir": [
        "",
        "int",
        "bool",
        "bool"
    ],
    "pathlib.Path.open": [
        "",
        "OpenTextMode",
        "int",
        "str | None",
        "str | None",
        "str | None"
    ],
    "pathlib.Path.resolve": [
        "",
        "bool"
    ],
    "pathlib.Path.rmdir": [
        ""
    ],
    "pathlib.Path.symlink_to": [
        "",
        "StrOrBytesPath",
        "bool"
    ],
    "pathlib.Path.touch": [
        "",
        "int",
        "bool"
    ],
    "pathlib.Path.home": [
        ""
    ],
    "pathlib.Path.absolute": [
        ""
    ],
    "pathlib.Path.expanduser": [
        ""
    ],
    "pathlib.Path.read_bytes": [
        ""
    ],
    "pathlib.Path.read_text": [
        "",
        "str | None",
        "str | None"
    ],
    "pathlib.Path.samefile": [
        "",
        "StrPath"
    ],
    "pathlib.Path.write_bytes": [
        "",
        "ReadableBuffer"
    ]
}