{
    "pythoncom.CoCreateFreeThreadedMarshaler": [
        "_win32typing.PyIUnknown"
    ],
    "pythoncom.CoCreateInstanceEx": [
        "_win32typing.PyIID",
        "_win32typing.PyIUnknown",
        "",
        "tuple[Incomplete, Incomplete, Incomplete, Incomplete]",
        "list[_win32typing.PyIID]"
    ],
    "pythoncom.CoCreateInstance": [
        "_win32typing.PyIID",
        "_win32typing.PyIUnknown | None",
        "int",
        "_win32typing.PyIID"
    ],
    "pythoncom.CoFreeUnusedLibraries": [],
    "pythoncom.CoInitialize": [],
    "pythoncom.CoInitializeEx": [
        ""
    ],
    "pythoncom.CoInitializeSecurity": [
        "_win32typing.PySECURITY_DESCRIPTOR",
        "",
        "",
        "",
        "",
        "",
        "",
        ""
    ],
    "pythoncom.CoGetInterfaceAndReleaseStream": [
        "_win32typing.PyIStream",
        "_win32typing.PyIID"
    ],
    "pythoncom.CoMarshalInterThreadInterfaceInStream": [
        "_win32typing.PyIID",
        "_win32typing.PyIUnknown"
    ],
    "pythoncom.CoMarshalInterface": [
        "_win32typing.PyIStream",
        "_win32typing.PyIID",
        "_win32typing.PyIUnknown",
        "",
        ""
    ],
    "pythoncom.CoUnmarshalInterface": [
        "_win32typing.PyIStream",
        "_win32typing.PyIID"
    ],
    "pythoncom.CoReleaseMarshalData": [
        "_win32typing.PyIStream"
    ],
    "pythoncom.CoGetObject": [
        "str",
        "_win32typing.PyIID",
        "Incomplete | None"
    ],
    "pythoncom.CoUninitialize": [],
    "pythoncom.CoRegisterClassObject": [
        "_win32typing.PyIID",
        "_win32typing.PyIUnknown",
        "",
        ""
    ],
    "pythoncom.CoResumeClassObjects": [],
    "pythoncom.CoRevokeClassObject": [
        ""
    ],
    "pythoncom.CoTreatAsClass": [
        "_win32typing.PyIID",
        "_win32typing.PyIID"
    ],
    "pythoncom.CoWaitForMultipleHandles": [
        "",
        "",
        "list[int]"
    ],
    "pythoncom.Connect": [
        ""
    ],
    "pythoncom.CreateGuid": [],
    "pythoncom.CreateBindCtx": [],
    "pythoncom.CreateFileMoniker": [
        "str"
    ],
    "pythoncom.CreateItemMoniker": [
        "str",
        "str"
    ],
    "pythoncom.CreatePointerMoniker": [
        "_win32typing.PyIUnknown"
    ],
    "pythoncom.CreateTypeLib": [],
    "pythoncom.CreateTypeLib2": [],
    "pythoncom.CreateStreamOnHGlobal": [
        "int | None",
        "bool"
    ],
    "pythoncom.CreateILockBytesOnHGlobal": [
        "int | None",
        "bool"
    ],
    "pythoncom.EnableQuitMessage": [
        ""
    ],
    "pythoncom.FUNCDESC": [],
    "pythoncom.GetActiveObject": [
        ""
    ],
    "pythoncom.GetClassFile": [
        ""
    ],
    "pythoncom.GetFacilityString": [
        ""
    ],
    "pythoncom.GetRecordFromGuids": [
        "_win32typing.PyIID",
        "",
        "",
        "",
        "_win32typing.PyIID",
        "Incomplete | None"
    ],
    "pythoncom.GetRecordFromTypeInfo": [
        "_win32typing.PyITypeInfo"
    ],
    "pythoncom.GetRunningObjectTable": [
        "int"
    ],
    "pythoncom.GetScodeString": [
        ""
    ],
    "pythoncom.GetScodeRangeString": [
        ""
    ],
    "pythoncom.GetSeverityString": [
        ""
    ],
    "pythoncom.IsGatewayRegistered": [
        "_win32typing.PyIID | None"
    ],
    "pythoncom.LoadRegTypeLib": [
        "_win32typing.PyIID",
        "",
        "",
        ""
    ],
    "pythoncom.LoadTypeLib": [
        "str"
    ],
    "pythoncom.MakePyFactory": [
        "_win32typing.PyIID"
    ],
    "pythoncom.MkParseDisplayName": [
        "str",
        "_win32typing.PyIBindCtx | None"
    ],
    "pythoncom.New": [
        ""
    ],
    "pythoncom.ObjectFromAddress": [
        "",
        "_win32typing.PyIID"
    ],
    "pythoncom.ObjectFromLresult": [
        "",
        "_win32typing.PyIID",
        ""
    ],
    "pythoncom.OleInitialize": [],
    "pythoncom.OleGetClipboard": [],
    "pythoncom.OleFlushClipboard": [],
    "pythoncom.OleIsCurrentClipboard": [
        "_win32typing.PyIDataObject"
    ],
    "pythoncom.OleSetClipboard": [
        "_win32typing.PyIDataObject"
    ],
    "pythoncom.OleLoadFromStream": [
        "_win32typing.PyIStream",
        "_win32typing.PyIID"
    ],
    "pythoncom.OleSaveToStream": [
        "_win32typing.PyIPersistStream",
        "_win32typing.PyIStream"
    ],
    "pythoncom.OleLoad": [
        "_win32typing.PyIStorage",
        "_win32typing.PyIID",
        "_win32typing.PyIOleClientSite"
    ],
    "pythoncom.ProgIDFromCLSID": [
        ""
    ],
    "pythoncom.PumpWaitingMessages": [
        "int",
        "int"
    ],
    "pythoncom.PumpMessages": [],
    "pythoncom.QueryPathOfRegTypeLib": [
        "_win32typing.PyIID",
        "",
        "",
        ""
    ],
    "pythoncom.ReadClassStg": [
        "_win32typing.PyIStorage"
    ],
    "pythoncom.ReadClassStm": [
        "_win32typing.PyIStream"
    ],
    "pythoncom.RegisterTypeLib": [
        "_win32typing.PyITypeLib",
        "str",
        "",
        "str | None"
    ],
    "pythoncom.UnRegisterTypeLib": [
        "_win32typing.PyIID",
        "",
        "",
        "",
        ""
    ],
    "pythoncom.RegisterActiveObject": [
        "_win32typing.PyIUnknown",
        "_win32typing.PyIID",
        ""
    ],
    "pythoncom.RevokeActiveObject": [
        ""
    ],
    "pythoncom.RegisterDragDrop": [
        "int",
        "_win32typing.PyIDropTarget"
    ],
    "pythoncom.RevokeDragDrop": [
        "int"
    ],
    "pythoncom.DoDragDrop": [],
    "pythoncom.StgCreateDocfile": [
        "str",
        "",
        "int"
    ],
    "pythoncom.StgCreateDocfileOnILockBytes": [
        "_win32typing.PyILockBytes",
        "",
        ""
    ],
    "pythoncom.StgOpenStorageOnILockBytes": [
        "_win32typing.PyILockBytes",
        "_win32typing.PyIStorage",
        "Incomplete | None",
        "int"
    ],
    "pythoncom.StgIsStorageFile": [
        "str"
    ],
    "pythoncom.STGMEDIUM": [],
    "pythoncom.StgOpenStorage": [
        "str",
        "_win32typing.PyIStorage",
        "",
        "Incomplete | None",
        ""
    ],
    "pythoncom.StgOpenStorageEx": [
        "str",
        "",
        "",
        "",
        "_win32typing.PyIID",
        "Incomplete | None"
    ],
    "pythoncom.StgCreateStorageEx": [
        "str",
        "",
        "",
        "",
        "_win32typing.PyIID",
        "Incomplete | None",
        "_win32typing.PySECURITY_DESCRIPTOR | None"
    ],
    "pythoncom.TYPEATTR": [],
    "pythoncom.VARDESC": [],
    "pythoncom.WrapObject": [
        "",
        "_win32typing.PyIID",
        "_win32typing.PyIID"
    ],
    "pythoncom.WriteClassStg": [
        "_win32typing.PyIStorage",
        "_win32typing.PyIID"
    ],
    "pythoncom.WriteClassStm": [
        "_win32typing.PyIStream",
        "_win32typing.PyIID"
    ],
    "pythoncom.UnwrapObject": [
        "_win32typing.PyIUnknown"
    ],
    "pythoncom.FmtIdToPropStgName": [
        "_win32typing.PyIID"
    ],
    "pythoncom.PropStgNameToFmtId": [
        "str"
    ],
    "pythoncom.CoGetCallContext": [
        "_win32typing.PyIID"
    ],
    "pythoncom.CoGetObjectContext": [
        "_win32typing.PyIID"
    ],
    "pythoncom.CoGetCancelObject": [
        "_win32typing.PyIID",
        "int"
    ],
    "pythoncom.CoSetCancelObject": [
        "_win32typing.PyIUnknown"
    ],
    "pythoncom.CoEnableCallCancellation": [],
    "pythoncom.CoDisableCallCancellation": [],
    "pythoncom.CreateURLMonikerEx": [],
    "pythoncom.new": [
        "_win32typing.PyIID | str"
    ],
    "pythoncom.connect": []
}