{
    "reprlib.Repr.repr": [
        "",
        "Any"
    ],
    "reprlib.Repr.repr1": [
        "",
        "Any",
        "int"
    ],
    "reprlib.Repr.repr_tuple": [
        "",
        "tuple[Any, ...]",
        "int"
    ],
    "reprlib.Repr.repr_list": [
        "",
        "list[Any]",
        "int"
    ],
    "reprlib.Repr.repr_array": [
        "",
        "array[Any]",
        "int"
    ],
    "reprlib.Repr.repr_set": [
        "",
        "set[Any]",
        "int"
    ],
    "reprlib.Repr.repr_frozenset": [
        "",
        "frozenset[Any]",
        "int"
    ],
    "reprlib.Repr.repr_deque": [
        "",
        "deque[Any]",
        "int"
    ],
    "reprlib.Repr.repr_dict": [
        "",
        "dict[Any, Any]",
        "int"
    ],
    "reprlib.Repr.repr_str": [
        "",
        "str",
        "int"
    ],
    "reprlib.Repr.repr_int": [
        "",
        "int",
        "int"
    ],
    "reprlib.Repr.repr_instance": [
        "",
        "Any",
        "int"
    ],
    "reprlib.recursive_repr": [
        "str"
    ],
    "reprlib.repr": [
        "object"
    ]
}