{
    "shutil.copyfile": [
        "StrOrBytesPath",
        "_StrOrBytesPathT"
    ],
    "shutil.copymode": [
        "StrOrBytesPath",
        "StrOrBytesPath"
    ],
    "shutil.copystat": [
        "StrOrBytesPath",
        "StrOrBytesPath"
    ],
    "shutil.copy": [
        "StrPath",
        "StrPath"
    ],
    "shutil.copy2": [
        "StrPath",
        "StrPath"
    ],
    "shutil.ignore_patterns": [],
    "shutil.disk_usage": [
        "FileDescriptorOrPath"
    ],
    "shutil.chown": [
        "StrOrBytesPath",
        "str | int",
        "None"
    ],
    "shutil.make_archive": [
        "str",
        "str",
        "StrPath | None",
        "StrPath | None",
        "bool",
        "bool",
        "str | None",
        "str | None",
        "Any | None"
    ],
    "shutil.get_archive_formats": [],
    "shutil.register_archive_format": [
        "str",
        "Callable[..., object]",
        "Sequence[tuple[str, Any] | list[Any]]",
        "str"
    ],
    "shutil.unregister_archive_format": [
        "str"
    ],
    "shutil.register_unpack_format": [
        "str",
        "list[str]",
        "Callable[..., object]",
        "Sequence[tuple[str, Any]]",
        "str"
    ],
    "shutil.unregister_unpack_format": [
        "str"
    ],
    "shutil.get_unpack_formats": [],
    "shutil.get_terminal_size": [
        "tuple[int, int]"
    ]
}