<?xml version="1.0" encoding="UTF-8"?>
<!--Copyright 2024 The MathWorks, Inc.-->

<rsccat xmlns:xsi="http://www.w3.org/2001/XMLSchema-instance" version="1.0" locale="zh_CN" product="MATLAB" xsi:noNamespaceSchemaLocation="../../../../../resources/schema/msgcat.xsd">
  <message>
    <entry key="InvalidTextInput">输入应为 cellstr、字符矩阵或字符串。</entry>
    <entry key="InvalidCharDimensions">应为二维字符数组。</entry>
    <entry key="InvalidStringDimensions">应为 M×1 字符串数组。</entry>
    <entry key="InvalidCellstrDimensions">应为 M×1 cellstr。</entry>
    <entry key="InvalidCellArray">应为仅包含字符向量的元胞数组。</entry>
    <entry key="UnrecognizedUTF16Character">Could not convert string in row {0, number, integer} to UTF-8:\n{1}</entry>
  </message>
</rsccat>
