<?xml version="1.0" encoding="UTF-8"?>
<!--Copyright 2024 The MathWorks, Inc.-->

<rsccat xmlns:xsi="http://www.w3.org/2001/XMLSchema-instance" version="1.0" locale="ja_JP" product="ros" xsi:noNamespaceSchemaLocation="../../resources/schema/msgcat.xsd">
  <message>
    <entry key="ShutdownError">ROS マスターのシャットダウン中にエラーが発生しました。</entry>
    <entry key="InvalidPort">他のアプリケーションで使用中であるため、端子 {0,number,integer} で ROS マスターを起動できませんでした。別の端子を使用する新しい ROS マスターを作成してください。</entry>
    <entry key="FailedToStart">端子 {0,number,integer} で ROS マスターを起動できませんでした</entry>
    <entry key="AlreadyRunning">ROS マスターは既にポート {0,number,integer} 上で実行されています。このマスターに接続するか、または別のポートを使用する新しい ROS マスターを作成してみてください。</entry>
    <entry key="InitializeROSCore">ROS コアを起動中...</entry>
    <entry key="InitializeGlobal">{0} 上の ROS マスターを初期化しています。</entry>
    <entry key="ShuttingDownGlobal">{0} 上の ROS マスターをシャットダウンしています。</entry>
    <entry key="GlobalCoreInvalidOp">無効な操作 {0} が ros.internal.Global.core の入力に使用されています。</entry>
    <entry key="GlobalCoreNotRunning">ROS マスターが初期化されていません。"rosinit" を引数なしで使用し、ROS マスターを起動してください。</entry>
    <entry key="MasterNotReachable">ROS マスターのシステムの状態を取得できませんでした。"rosshutdown" を呼び出してグローバル ノードをシャットダウンしてから、"rosinit" を呼び出して ROS マスターを起動してください。</entry>
  </message>
</rsccat>
