<?xml version="1.0" encoding="UTF-8"?>
<!--Copyright 2025 The MathWorks, Inc.-->

<rsccat xmlns:xsi="http://www.w3.org/2001/XMLSchema-instance" version="1.0" locale="ja_JP" product="SDI" xsi:noNamespaceSchemaLocation="../../resources/schema/msgcat.xsd">
  <message>
    <entry key="OK">OK</entry>
    <entry key="Cancel">キャンセル</entry>
    <entry key="Close">閉じる</entry>
    <entry key="MGExportDataTitleDesc">MAT ファイルにラベルの定義をエクスポートします</entry>
    <entry key="LabelDefDefaultVarName">lblDefs</entry>
    <entry key="LabelDefDefaultFileName">lblDefs.mat</entry>
    <entry key="InValidVariableName">変数名は有効な MATLAB 変数名でなければなりません。</entry>
    <entry key="MGAcceptAllTitle">ラベルの保存</entry>
    <entry key="MGAcceptAllExportDataTitleDesc">ラベルを保存して、信号アナライザーに戻ります。</entry>
    <entry key="mgExportDataVarName"> ラベル付き信号セット変数名:</entry>
    <entry key="mgExportOverwriteVariableWarn">既存の変数を上書きしますか?</entry>
    <entry key="LSSDefaultVarName">ls</entry>
    <entry key="CancelLabelingTitle">キャンセル</entry>
    <entry key="CancelLabelingWarningMsg"> すべてのラベル付けをキャンセルしますか?保存されていないラベルは削除されます。</entry>
    <entry key="mgClearRunsWarn">信号アナライザーを閉じますか? 保存されていない信号アナライザー データとラベル データはすべて失われます。</entry>
    <entry key="mgSaveSessionTitle">閉じる</entry>
    <entry key="AddLabelTitle">ラベルの定義の追加</entry>
    <entry key="EditLabelTitle">ラベルの定義の編集</entry>
    <entry key="AddSubLabelTitle">サブラベルの定義の追加</entry>
    <entry key="EditSubLabelTitle">サブラベルの定義の編集</entry>
    <entry key="AddLabelDefParentNameLabel">親の名前:</entry>
    <entry key="AddLabelDefNameLabel">ラベル名</entry>
    <entry key="AddLabelDefTypeLabel">ラベル タイプ</entry>
    <entry key="AddLabelDescriptionLabel">ラベルの説明</entry>
    <entry key="AddLabelDataTypeLabel">データ型</entry>
    <entry key="AddLabelCategoriesLabel">カテゴリ</entry>
    <entry key="AddLabelCategoriesLabelDesc">各カテゴリを 1 行ごとに入力します</entry>
    <entry key="AddLabelDefaultLabel">既定の設定</entry>
    <entry key="AddLabelTextWarning">無効なラベルの定義名</entry>
    <entry key="AddLabelOptionalLabel">オプション</entry>
    <entry key="AddLabelAttribute">属性</entry>
    <entry key="AddLabelROI">ROI</entry>
    <entry key="AddLabelPoint">点</entry>
    <entry key="EditFeatureROI">特徴の ROI</entry>
    <entry key="EditFeatureAttribute">特徴属性</entry>
    <entry key="AddLabelTimeFrequencyROI">時間-周波数 ROI</entry>
    <entry key="AddLabelString">string</entry>
    <entry key="AddLabelNumeric">数値</entry>
    <entry key="AddLabelLogical">logical</entry>
    <entry key="AddLabelCatagorical">categorical</entry>
    <entry key="AddLabelTrue">true</entry>
    <entry key="AddLabelFalse">false</entry>
    <entry key="LabelSignalTitle">すべてにラベル付け</entry>
    <entry key="LabelSignalLabelAllRadioLabel">すべてのメンバー</entry>
    <entry key="LabelSignalLabelSelectedRadioLabel">メンバーを選択</entry>
    <entry key="LabelPlottedSignalTitle">プロット済み信号のラベル付け</entry>
    <entry key="UpdateLabelInstanceTitle">ラベルの編集</entry>
    <entry key="LabelValue">値:</entry>
    <entry key="LabelLocation">場所</entry>
    <entry key="LabelLocationMin">最小値</entry>
    <entry key="LabelLocationMax">最大値</entry>
    <entry key="LabelLocationTime">時間の位置</entry>
    <entry key="LabelLocationFrequency">周波数の位置</entry>
    <entry key="SelectSignals">選択</entry>
    <entry key="NameColumn">名前</entry>
    <entry key="ImportDialogOk">インポート</entry>
    <entry key="ImportDialogTitle">インポート</entry>
    <entry key="ImportDialogTitleDesc">MAT ファイルからラベルの定義をインポートします</entry>
    <entry key="FileNameLabel">ファイル名:</entry>
    <entry key="NoLabelDefinitionsErrorMsg">ファイルにタイプ 'signalLabelDefinition' の有効なデータが含まれていません。</entry>
    <entry key="AutoLabelSignalsTitle">信号の自動ラベル付け</entry>
    <entry key="UnitsSeconds">s</entry>
    <entry key="UnitsSamples">サンプル</entry>
    <entry key="RestoreDefaultSettingsBtnLabel">既定の設定に戻す</entry>
    <entry key="RestoreDefaultSettingsBtnDesc">既定の設定に戻します</entry>
    <entry key="PeakLabelerHeaderLabel">設定 - ピーク ラベラー</entry>
    <entry key="MaxNumPeakLabel">ピーク数:</entry>
    <entry key="MaxNumPeakAllLabel">すべて</entry>
    <entry key="AtMostNumPeakLabel">最大</entry>
    <entry key="FindLocalLabel">ローカルを検索:</entry>
    <entry key="FindLocalMaximaLabel">最大値</entry>
    <entry key="FindLocalMinimaLabel">最小値</entry>
    <entry key="ProminenceAtLeastLabel">最小プロミネンス:</entry>
    <entry key="ProminenceWindowLabel">プロミネンス ウィンドウ ({0}):</entry>
    <entry key="FlatRegionPointLabel">フラット領域の点:</entry>
    <entry key="FlatRegionPointCenterLabel">中央</entry>
    <entry key="FlatRegionPointFirstLabel">最初</entry>
    <entry key="FlatRegionPointLastLabel">最後</entry>
    <entry key="FlatRegionPointAllLabel">すべて</entry>
    <entry key="MinSeperationLabel">最小間隔 ({0}):</entry>
    <entry key="InvalidNumericValue">値は数値でなければなりません。</entry>
    <entry key="CustomLabelerHeaderLabel">設定 - カスタム ラベラー</entry>
    <entry key="CustomLabelerFunctionNameLabel">関数: {0}</entry>
    <entry key="CustomLabelerArgsLabel">引数: </entry>
    <entry key="CustomLabelerArgsNonLabel">なし</entry>
    <entry key="AutoLabelFuctionTitle">カスタム関数の追加</entry>
    <entry key="AutoLabelFuctionName">名前:</entry>
    <entry key="AutoLabelFuctionDescription">説明:</entry>
    <entry key="AutoLabelFuctionDescriptionPlaceHolder">オプションの入力引数 'arg1、arg2' をもつマイ カスタム関数</entry>
    <entry key="AutoLabelFuctionLabelType">ラベル タイプ:</entry>
    <entry key="FunctionAPIInfoHeaderLabel">次の構文によって、関数を自動ラベリング関数ギャラリーに追加します。</entry>
    <entry key="FunctionAPIInfoLabel">[labelVals,labelLocs] = fx(x,t,parentLabelVal,parentLabelLoc,varargin)</entry>
    <entry key="FunctionAPIInfoLabelTimeFrequencyROI">[labelVals,labelLocsTime,labelLocsFreq] = fx(x,tf,t,f,tfOptions,varargin)</entry>
    <entry key="FunctionAPIDescriptionLabel">x (選択した信号)、t (その時間ベクトル)、引数 parentLabelVal および parentLabelLoc は自動的にこの関数に\n渡されます。オプションの入力引数リストも指定できます。</entry>
    <entry key="FunctionAPIDescriptionLabelTimeFrequencyROI">x (時間内に選択した信号)、tf (x の時間-周波数変換)、t (時間ベクトル)、f (周波数ベクトル)、および\ntfOptions (tf を作成するオプション) は自動的にこの関数に渡されます。オプションの入力引数リストも\n指定できます。</entry>
    <entry key="AutoLabelFuctionCreateTitle">カスタム関数の作成</entry>
    <entry key="AutoLabelFuctionCreateFileMsgStart">ファイル</entry>
    <entry key="AutoLabelFuctionCreateFileMsgEnd">は存在しません。&lt;br&gt;作成しますか?</entry>
    <entry key="AutoLabelFuctionEditDescTitle">カスタム関数の説明の編集</entry>
    <entry key="AutoLabelFuctionEditDescSubTitle">自動ラベリング関数ギャラリーのカスタム関数の説明を編集します。</entry>
    <entry key="AutoLabelFuctionEditDescFunctionLabel">名前:</entry>
    <entry key="AutoLabelFuctionEditDescInputLabel">説明:</entry>
    <entry key="AutoLabelFuctionManageTitle">カスタム関数の管理</entry>
    <entry key="AutoLabelFuctionManageSubTitle">MATLAB エディターでの関数の編集、説明の編集、または自動ラベリング関数ギャラリーからの削除。</entry>
    <entry key="AutoLabelFuctionManageEditBtn">関数の編集</entry>
    <entry key="AutoLabelFuctionManageEditDescBtn">説明の編集</entry>
    <entry key="AutoLabelFuctionManageTableHeaderCol1">選択</entry>
    <entry key="AutoLabelFuctionManageTableHeaderCol2">関数</entry>
    <entry key="AutoLabelFuctionManageRemoveBtn">削除</entry>
    <entry key="MessageDialogDoNotShowAgainLabel">次回から表示しない。</entry>
    <entry key="AutoLabelSuccessInfoDialogTitle">選択した定義の信号の自動ラベル付け</entry>
    <entry key="AutoLabelSuccessInfoMsgForLabelsWithRunTimeLImits">{2} から {3} 内で {0} 個の {1} ラベルが、{4} を使用して {5} 個の信号に自動的に追加されました。</entry>
    <entry key="AutoLabelSuccessInfoMsgForSubLabelsWithRunTimeLImits">{2} から {3} 内で {0} 個の {1} サブラベルが、{4} を使用して {5} 個の信号に自動的に追加されました。</entry>
    <entry key="AutoLabelSuccessInfoMsgForLabels">{0} 個の {1} ラベルが、{2} を使用して {3} 個の信号に自動的に追加されました。</entry>
    <entry key="AutoLabelSuccessInfoMsgForSubLabels">{0} 個の {1} サブラベルが、{2} を使用して {3} 個の信号に自動的に追加されました。</entry>
    <entry key="AutoLabelErrorDialogTitle">選択した定義の信号の自動ラベル付け</entry>
    <entry key="CannotWriteInCurrentFolderMsg">MATLAB で現在のフォルダーを変更して再度実行してください。次のフォルダーへの書き込み権限がありません: </entry>
    <entry key="InvalidFunctionNameWarning">有効な MATLAB 関数名を指定してください</entry>
    <entry key="EmptyFunctionNameWarning">関数名を指定してください</entry>
    <entry key="mgWarn">警告</entry>
    <entry key="EmptyLabelDefNameText">ラベル名は有効な MATLAB 変数名でなければなりません。</entry>
    <entry key="DuplicateLabelDefNameText">新規および既存のラベル名は一意でなければなりません。</entry>
    <entry key="UnsupportedLabelDefinitionImport">少なくとも 1 つのラベルのデータ型が timetable または table であるため、1 つ以上の &lt;br /&gt;signalLabelDefinition オブジェクトをインポートできません。</entry>
    <entry key="EmptyLabelCategoriesText">カテゴリは指定しなければなりません。</entry>
    <entry key="EmptyStringLabelValue">値は string でなければなりません。</entry>
    <entry key="InvalidLabelValue">値は数値でなければなりません。</entry>
    <entry key="InvalidLocationValue">場所値は double でなければなりません。</entry>
    <entry key="TmaxLessThanTMinValue">位置 (最小) の値は位置 (最大) の値以下でなければなりません。</entry>
    <entry key="FmaxLessThanFMinValue">周波数の位置 (最小) の値は周波数の位置 (最大) の値以下でなければなりません。</entry>
    <entry key="SelectParentLabelForSubLabel">{0} ラベルを選択してからその {1} サブラベルにラベルを付けます。&lt;br /&gt;時間プロットで選択する場合は [パンおよび選択] モードを使用し、次に [ラベルの描画] モード (Ctrl+L) を使用して描画します。</entry>
    <entry key="ImportMixedTimeSignalsWarning">時間情報を含む信号と含まない信号に、同時にラベルを付けることはできません。テーブルの選択を変更してください。</entry>
    <entry key="InvalidConcatLabelDefinitions">選択したラベル付き信号セットのラベルの定義は同一でなければなりません。</entry>
    <entry key="NonUniqueMemberNames">同等のメンバー名を含む複数のラベル付き信号セットにラベルを付けることはできません。各セットに個別にラベルを付けるか、メンバーの名前が一意になるように変更してください。</entry>
    <entry key="ImportComplexSignalsWarning">複素信号にラベル付けできません。テーブルの選択を変更してください。</entry>
    <entry key="AutoLabelSignalsFailedMsg">次のエラーにより、信号がラベル付けされませんでした: {0}</entry>
    <entry key="OnCleanupMsg">自動ラベル付けのアクションが中断されました。</entry>
    <entry key="MustBeNumeric">値は数値でなければなりません。</entry>
    <entry key="MustBeLogical">値は logical でなければなりません。</entry>
    <entry key="MustBeString">値はスカラー string または char でなければなりません。</entry>
    <entry key="InvalidCategoryValue">値は string スカラーまたは char であるか、'Categorical' プロパティで定義された名前セットのサブセットである値セットまたは名前セットと同じ値セットをもつ categorical でなければなりません。順序 categorical はサポートされません。</entry>
    <entry key="InvalidROILimits">ラベルの位置範囲の各行に含まれる値のペアは、昇順でなければなりません。</entry>
    <entry key="IncorrectNumcols">ラベル値の数は、ラベル位置の行数と一致しなければなりません。</entry>
    <entry key="InvalidMultipleRegions">ラベル値の各行はスカラーでなければなりません。</entry>
    <entry key="InvalidLabelValueDimension">ラベル値は列ベクトルでなければなりません</entry>
    <entry key="InvalidLabelValueDimensionAttribute">ラベル値はスカラーでなければなりません</entry>
    <entry key="InvalidLocationDimensionAttribute">位置の値は空でなければなりません</entry>
    <entry key="InvalidLocationDimensionPoint">位置の値は列ベクトルでなければなりません</entry>
    <entry key="InvalidLocationDimensionROI">位置の値は 2 列の行列でなければなりません</entry>
    <entry key="InvalidNumberOfTimeAndFrequencyLimits">時間範囲の数は周波数範囲の数と一致する必要があります。</entry>
    <entry key="AutoLabelingModeCancelLabelingTitle">キャンセル</entry>
    <entry key="AutoLabelingModeCancelLabelingWarningMsg"> キャンセルしますか?自動ラベル付けで作成されたすべてのラベルが削除されます。</entry>
    <entry key="FastLabelSignalSelectionTitle">チャネル選択</entry>
    <entry key="FastLabelSignalSelectionSignalHeader">チャネル</entry>
    <entry key="ImportSignalsFromWorkspaceDialogTitle">ワークスペースからメンバーをインポート</entry>
    <entry key="ImportSignalsFromWorkspaceImportButton">インポート</entry>
    <entry key="ImportSignalsFromWorkspaceImportAndCloseButton">インポートして閉じる</entry>
    <entry key="ImportLabelDesc">インポートする変数を選択します</entry>
    <entry key="ImportWSBFilterNoneLabelDesc">絞り込み条件: サポートされているすべての変数</entry>
    <entry key="ImportWSBFilterInMemoryAndSamplesLabelDesc">絞り込み条件: サンプルでサポートされているインメモリ データをもつ変数</entry>
    <entry key="ImportWSBFilterInMemoryAndTimeLabelDesc">絞り込み条件: 時間でサポートされているインメモリ データをもつ変数</entry>
    <entry key="ImportWSBFilterFilesLabelDesc">絞り込み条件: ファイルを指す変数</entry>
    <entry key="SetTimeLabel">選択した変数の時間情報を設定</entry>
    <entry key="SetTimeLabelDisclaimer">固有の時間情報をもつ変数の場合、設定は無視されます。</entry>
    <entry key="TimeValuePlaceHolderTextFs">サンプルレートの設定</entry>
    <entry key="TimeValuePlaceHolderTextTs">サンプル時間の設定</entry>
    <entry key="TimeValuePlaceHolderTextTv">時間値の設定</entry>
    <entry key="TimeModeLabel">作業単位:</entry>
    <entry key="WorkInSamples">サンプル</entry>
    <entry key="WorkInTime">時間</entry>
    <entry key="WorkWithFiles">サンプルまたは時間 (ファイルから推定)</entry>
    <entry key="SampleRateTimeSpec">サンプルレート</entry>
    <entry key="SampleTimeTimeSpec">サンプル時間</entry>
    <entry key="TimeValuesTimeSpec">時間値</entry>
    <entry key="Years">年</entry>
    <entry key="Days">日</entry>
    <entry key="Hours">時間</entry>
    <entry key="Minutes">分</entry>
    <entry key="InvalidTimeMetadataTimeValuesSize">時間値は、選択した変数と同じ長さのベクトルでなければなりません。</entry>
    <entry key="AllNonUniqueMemberNames">インポートできません。メンバー名は、既にインポート済みのメンバーと一致しなければなりません。</entry>
    <entry key="LSSConcatenationIncompatibilityBetweenSelections">選択したラベル付き信号セットは、互換性のないラベルの定義があるためインポートされませんでした。選択内容を変更してください。</entry>
    <entry key="LSSInvalidLabelDefType">インポートできません。timetable または table のラベル データ型をもつラベルの定義はサポートされていません。</entry>
    <entry key="LSSFailedConcatenationWithExistingLSS">選択したラベル付き信号セットは、ラベルの定義が信号ラベラー アプリのラベルの定義と互換性がないためインポートされませんでした。選択内容を変更してください。</entry>
    <entry key="LSSFailedMergeLabelDefinitions">インポートできません。同じ名前をもつラベルの定義は一致しなければなりません。</entry>
    <entry key="LSSFailedMergeMembers">インポートできません。メンバー名は固有でなければなりません。</entry>
    <entry key="LSSFailedUnsupportedLabelDefsOrData">選択したラベル付き信号セットをインポートできません。ラベルのデータ型が timetable、table または非スカラーであるラベルの定義はサポートされていません。</entry>
    <entry key="ImportDisabledLSSTimeIncompatible">選択したラベル付き信号セットをインポートできません。ラベル付き信号セットのすべてに時間情報があるか、すべてに時間情報がないかのどちらかでなければなりません。</entry>
    <entry key="ImportDisabledLSSAndVarsTimeIncompatible">選択した変数をインポートできません。変数のすべてに時間情報があるか、すべてに時間情報がないかのどちらかでなければなりません。</entry>
    <entry key="ImportDisabledTimeIncompatibleWithSamplesMode">インポートできません。既にインポートされたメンバーには時間情報がありません。</entry>
    <entry key="ImportDisabledTimeIncompatibleWithTimeMode">インポートできません。既にインポートされたメンバーには時間情報があります。</entry>
    <entry key="ImportDisabledSelectVariables">ワークスペース ブラウザーから変数を選択してください。</entry>
    <entry key="ImportInvalidTimeInherentDataWarn">サポートされていない値が含まれているため、少なくとも 1 つの timetable またはラベル付き信号セットをインポートできません。サポートされる値の詳細については、ドキュメンテーションを参照してください。</entry>
    <entry key="ImportDisabledLSSSourceIncompatible">選択したラベル付き信号セットをインポートできません。ラベル付き信号セットのすべてに、ファイルを指すデータストアまたはインメモリ データがなければなりません。</entry>
    <entry key="ImportDisabledLSSAndVariableIncompatible">選択した変数をインポートできません。すべての変数は、インメモリ データを含むか、ファイルを指すデータストアをもつラベル付き信号セットでなければなりません。</entry>
    <entry key="ImportDisabledLSSSourceInvalid">選択したラベル付き信号セットをインポートできません。ラベル付き信号セットすべてにインメモリ データがなければなりません。</entry>
    <entry key="InvalidMergeSources">インポートできません。ラベル付き信号セットのデータストアは同じタイプでなければなりません。</entry>
    <entry key="InvalidMergeTimeInfo">インポートできません。ラベル付き信号セットの時間情報は同じタイプでなければなりません。</entry>
    <entry key="IncompatibleTimeInformation">インポートできません。ラベル付き信号セットのデータストアの時間情報には互換性がなければなりません。</entry>
    <entry key="IncompatibleFileTypes">インポートできません。すべてのファイルの拡張子は、既にインポートされているファイルと同じでなければなりません。</entry>
    <entry key="IncompatibleSignalVariableNames">インポートできません。すべてのラベル付き信号セットは、'SignalVariableNames' データストア プロパティが指定されていないか、このプロパティが同じ値で指定されていなければなりません。</entry>
    <entry key="IncompatibleSampleRateVariableName">インポートできません。すべてのラベル付き信号セットは、'SampleRateVariableName' データストア プロパティが指定されていないか、このプロパティが同じ値で指定されていなければなりません。</entry>
    <entry key="IncompatibleSampleTimeVariableName">インポートできません。すべてのラベル付き信号セットは、'SampleTimeVariableName' データストア プロパティが指定されていないか、このプロパティが同じ値で指定されていなければなりません。</entry>
    <entry key="IncompatibleTimeValuesVariableName">インポートできません。すべてのラベル付き信号セットは、'TimeValuesVariableName' データストア プロパティが指定されていないか、このプロパティが同じ値で指定されていなければなりません。</entry>
    <entry key="IncompatibleLabelWarning">インポートされるラベル付き信号セットのすべてのラベルに実数のスカラー値がなければなりません。一部のラベルがインポートされませんでした。</entry>
    <entry key="InvalidMemberDataInforNan">インポートできません。ラベル付き信号セット データは有限値である必要があります。</entry>
    <entry key="ImportSignalsFromFileImportButton">インポート</entry>
    <entry key="ImportSignalsFromFileDialogTitle">ファイルからのメンバーのインポート</entry>
    <entry key="ImportSignalsFromFileDialogNameLabel">名前</entry>
    <entry key="ImportSignalsFromFileExtensionLabel">拡張子</entry>
    <entry key="ImportSignalsFromFileAutoSignalVarNameLabel">最初の信号変数</entry>
    <entry key="ImportSignalsFromFileSpecifySignalVarNameLabel">指定</entry>
    <entry key="ImportSignalsFromFileSpecifyPlaceholder">コンマ区切りの名前を入力してください</entry>
    <entry key="ImportSignalsFromFileSignalVarNameLabel">信号変数</entry>
    <entry key="MatFileItemLabel">MAT ファイル</entry>
    <entry key="CsvFileItemLabel">CSV</entry>
    <entry key="TimeInfoLabel">時間情報</entry>
    <entry key="AutoTimeInfoCheckboxLabel">信号変数から推定</entry>
    <entry key="AutoTimeInfoLabelValue">信号変数から推定済み</entry>
    <entry key="SpecifyTimeInfoCheckboxLabel">作業単位</entry>
    <entry key="SampleRateVariableNameItemLabel">ファイルからのサンプル レート変数</entry>
    <entry key="SampleTimeVariableNameItemLabel">ファイルからのサンプル時間変数</entry>
    <entry key="TimeValuesVariableNameItemLabel">ファイルからの時間値変数</entry>
    <entry key="TimeInfoVariableNamePlaceholder">変数名を入力します</entry>
    <entry key="SampleRateItemLabel">サンプルレート</entry>
    <entry key="SampleTimeItemLabel">サンプル時間</entry>
    <entry key="TimeValuesItemLabel">時間値</entry>
    <entry key="TimeInfoValuesPlaceholder">コンマ区切りの値を入力してください</entry>
    <entry key="InvalidImportToFileNameWarning">ファイル名を指定</entry>
    <entry key="ImportSignalsFromFolderDialogTitle">フォルダーからのメンバーのインポート</entry>
    <entry key="ImportSignalsFromFolderDialogNameLabel">名前</entry>
    <entry key="ImportSignalsFromFileIncludeSubFolderLabel">サブフォルダーを含む</entry>
    <entry key="ImportSignalsFromFileInferedMsg">{0} 個のファイルがインポートされました。プロット時に、データはサンプル内に、または推定時間情報に基づく時系列で表示されます。</entry>
    <entry key="ImportSignalsFromFileInSampleMsg">{0} 個のファイルがインポートされました。プロット時に、データはサンプル内に表示されます。</entry>
    <entry key="ImportSignalsFromFileInTimeMsg">{0} 個のファイルがインポートされました。プロット時に、データは時系列で表示されます。</entry>
    <entry key="ImportFromFileNotificationInitMsg">初期化中</entry>
    <entry key="ImportFromFileNotificationMsg">{1} 個中 {0} 個のファイルから信号データを読み取っています。</entry>
    <entry key="LazyLoadDataNotificationTitle">ファイルからのデータの読み取り</entry>
    <entry key="LazyLoadDataFailedTitle">ファイルからのデータの読み取り</entry>
    <entry key="InvalidFsOrTsValueOfTimeVariableInFile">ファイル ''{0}'' のデータを読み取れません。''{1}'' 変数は実数値をもたなければなりません。</entry>
    <entry key="InvalidTimeValuesOfTimeVariableInFile">ファイル ''{0}'' のデータを読み取れません。''{1}'' 変数は並べ替えられた実数値をもたなければなりません。</entry>
    <entry key="InvalidTimeInherentDataInFile">ファイル ''{0}'' のデータを読み取れません。''{1}'' 変数は並べ替えられた等間隔時間の実数値をもたなければなりません。</entry>
    <entry key="NonNumericDataValueInFile">ファイル ''{0}'' のデータを読み取れません。''{1}'' 変数は実数値をもたなければなりません。</entry>
    <entry key="InvalidDataWithMixedTime">ファイル ''{0}'' のデータを読み取れません。''{1}'' の変数は同じ時間情報をもたなければなりません。</entry>
    <entry key="InvalidDataWithMixedTimeTable">ファイル ''{0}'' のデータを読み取れません。''{1}'' の変数は同じ時間情報をもたなければなりません。</entry>
    <entry key="InvalidDataWithTime">ファイル ''{0}'' のデータを読み取れません。''{1}'' 変数はサンプル内になければなりません。</entry>
    <entry key="InvalidDataWithOutTime">ファイル ''{0}'' のデータを読み取れません。''{1}'' 変数は時間情報をもたなければなりません。</entry>
    <entry key="InvalidDataAndTimeValuesDims">ファイル ''{0}'' のデータを読み取れません。時間値は、変数 ''{1}'' のデータと同じ長さのベクトルでなければなりません。</entry>
    <entry key="LazyLoadFailedRemoveFileErrorMsg">信号ラベラーからファイルを削除しますか?</entry>
    <entry key="DefaultFilesNotFound">指定されたファイルの場所には、既定でサポートされているファイル拡張子をもつファイルがありません。</entry>
    <entry key="InvalidSampleRateDims">'SampleRate' はスカラーか、または指定したファイル数と同じ長さをもつ順序付けされたコンマ区切りのスカラーのリストでなければなりません。</entry>
    <entry key="InvalidSampleTimeDims">'SampleTime' はスカラーか、または指定したファイル数と同じ長さをもつ順序付けされたコンマ区切りのスカラーのリストでなければなりません。</entry>
    <entry key="InvalidTimeValuesDims">'TimeValues' はベクトルか、または指定したファイル数と同じ長さをもつ順序付けされたコンマ区切りのベクトルのリストでなければなりません。</entry>
    <entry key="InvalidMergeMembers">インポートできません。すべてのファイルの絶対ファイル パス名は一意でなければなりません。</entry>
    <entry key="MATDesc2">MAT ファイル</entry>
    <entry key="ExportDialogExportButton">エクスポート</entry>
    <entry key="OverwriteVariableInWorkspaceMsg">ベース ワークスペースで既存の変数を上書きしますか?</entry>
    <entry key="OverwriteVariableInWorkspaceTitle">変数の上書き</entry>
    <entry key="OverwriteFileContentMsg">現在のディレクトリにある既存のファイルを上書きしますか?</entry>
    <entry key="OverwriteFileContentTitle">ファイルの上書き</entry>
    <entry key="ExportLSSToWorkspaceDialogTitle">ラベル付き信号セットをワークスペースにエクスポート</entry>
    <entry key="ExportLSSToWorkspaceDialogNameLabel">名前</entry>
    <entry key="ExportLSSToWorkspaceDialogDescriptionLabel">説明</entry>
    <entry key="InvalidExportToWSNameWarning">名前は有効な MATLAB 変数名でなければなりません</entry>
    <entry key="ExportLabelDefToWorkspaceDialogTitle">ラベルの定義をワークスペースにエクスポート</entry>
    <entry key="ExportLabelDefToWorkspaceDialogNameLabel">名前</entry>
    <entry key="ExportLSSToFileDialogTitle">ラベル付き信号セットをファイルにエクスポート</entry>
    <entry key="ExportLSSToFileDialogNameLabel">名前</entry>
    <entry key="ExportLSSToFileDialogDescriptionLabel">説明</entry>
    <entry key="InvalidExportToFileNameWarning">ファイル名を指定してください</entry>
    <entry key="ExportLabelDefToFileDialogTitle">ラベルの定義をファイルにエクスポート</entry>
    <entry key="ExportLabelDefToFileDialogNameLabel">名前</entry>
    <entry key="NewSessionTitle">新規セッション</entry>
    <entry key="NewSessionMessage">新しいセッションを開始しますか? エクスポートしていないデータはすべて失われます。</entry>
    <entry key="CloseMessage">信号ラベラーを閉じますか? エクスポートしていないデータはすべて失われます。</entry>
    <entry key="MultiSignalSelectedWithSpectrogramOn">複数の信号のスペクトログラムをプロットすることはできません。スペクトログラム表示をオフにするか、選択を変更してください。</entry>
    <entry key="featureExtractionChannelSelectionHeaderMsg">特徴抽出に使用するメンバー チャネルを選択します。</entry>
    <entry key="FeatureExtractionDlgOKBtnLabel">実行</entry>
    <entry key="FeatureExtractionDlgTimeTitle">時間領域の特徴を生成</entry>
    <entry key="FeatureExtractionDlgFreqTitle">周波数領域の特徴を生成</entry>
    <entry key="FeatureExtractionCancelLabelingTitle">キャンセル</entry>
    <entry key="FeatureExtractionCancelLabelingWarningMsg"> キャンセルしますか?抽出されたすべての特徴は削除されます。</entry>
    <entry key="FeatureExtractionSelectFeaturesLabel">抽出する特徴の選択</entry>
    <entry key="FeatureExtractionFeatureParameters">パラメーター</entry>
    <entry key="FeatureExtractionNotificationTitle">特徴抽出</entry>
    <entry key="FeatureExtractionNotificationInitMsg">初期化しています。</entry>
    <entry key="FeatureExtractionFeatureNotificationMsg">{1} 個中 {0} 個のメンバーの特徴を抽出しています。</entry>
    <entry key="FeatureExtractionFeatureDefNotificationMsg">{1} 個中 {0} 個の特徴のラベルの定義を作成しています。</entry>
    <entry key="Mean">平均</entry>
    <entry key="RMS">RMS</entry>
    <entry key="StandardDeviation">標準偏差</entry>
    <entry key="ShapeFactor">形状係数</entry>
    <entry key="SNR">SNR</entry>
    <entry key="THD">THD</entry>
    <entry key="SINAD">SINAD</entry>
    <entry key="PeakValue">ピーク値</entry>
    <entry key="CrestFactor">クレスト ファクター</entry>
    <entry key="ClearanceFactor">クリアランス係数</entry>
    <entry key="ImpulseFactor">インパルス係数</entry>
    <entry key="FeatureExtractionStatisticsLabel">統計</entry>
    <entry key="FeatureExtractionPulseMetricsLabel">パルス メトリクス</entry>
    <entry key="FeatureExtractionHarmonicsLabel">高調波</entry>
    <entry key="UnitsHZ">Hz</entry>
    <entry key="UnitsRadians">ラジアン/サンプル</entry>
    <entry key="UnitsPiRadians">\u03C0 r/サンプル</entry>
    <entry key="FeatureExtractionSetFeatureWelchParameters">選択した特徴に使用されているウェルチ PSD のパラメーターを指定 </entry>
    <entry key="MeanFrequency">周波数平均値</entry>
    <entry key="MedianFrequency">周波数中央値</entry>
    <entry key="BandPower">帯域パワー</entry>
    <entry key="OccupiedBandwidth">占有帯域幅</entry>
    <entry key="PowerBandwidth">パワー帯域幅</entry>
    <entry key="FeatureExtractionWindowLengthLabel">ウィンドウの長さ ({0})</entry>
    <entry key="FeatureExtractionWindowParamLabel">ウィンドウ パラメーター</entry>
    <entry key="FeatureExtractionOverlapLabel">オーバーラップの長さ ({0})</entry>
    <entry key="FeatureExtractionSpecifyFreqLabel">[FFT 長] または [周波数ベクトル] を指定</entry>
    <entry key="FeatureExtractionFFTLengthLabel">FFT 長</entry>
    <entry key="FeatureExtractionFrequencyVectorLabel">周波数ベクトル ({0})</entry>
    <entry key="FeatureExtractionFrequencyMinLabel">最小値</entry>
    <entry key="FeatureExtractionFrequencyMaxLabel">最大値</entry>
    <entry key="FeatureExtractionFrequencyLengthLabel">長さ</entry>
    <entry key="FeatureExtractionHamming">ハミング</entry>
    <entry key="FeatureExtractionHann">ハン</entry>
    <entry key="FeatureExtractionKaiser">カイザー</entry>
    <entry key="FeatureExtractionRectangular">矩形</entry>
    <entry key="FeatureExtractionChebyshev">チェビシェフ</entry>
    <entry key="FeatureExtractionBarlett">バートレット</entry>
    <entry key="FeatureExtractionBlackman">ブラックマン</entry>
    <entry key="FeatureExtractionFlatTop">フラット トップ</entry>
    <entry key="FeatureExtractionGaussian">ガウス</entry>
    <entry key="FeatureExtractionNuttall">Nuttall</entry>
    <entry key="FeatureExtractionTriangular">三角形</entry>
    <entry key="InvalidNonPositiveNumericValueError">値は正の数値でなければなりません。</entry>
    <entry key="InvalidNonPositiveIntegerValueError">値は正の整数でなければなりません。</entry>
    <entry key="InvalidIntegerValueLessThanTwoError">値は 2 以上の正の整数である必要があります。</entry>
    <entry key="OverLapLengthGreaterThanWindowLengthError">オーバーラップの長さはウィンドウの長さより小さくなければなりません。</entry>
    <entry key="FreqMinGreaterThanFreqMaxError">周波数の最小値は周波数の最大値より小さくなければなりません。</entry>
    <entry key="OccupiedBandwidthPercentageLabel">割合</entry>
    <entry key="OccupiedBandwidthPercentageError">値は 100 未満の正の数値でなければなりません。</entry>
    <entry key="PowerBandwidthAmplitudeLabel">相対振幅 (db)</entry>
    <entry key="PowerBandwidthAmplitudeError">値は数値でなければなりません。</entry>
    <entry key="FullSignalFeatueDefinitionDescription">信号全体の {0} が、信号ラベラー {1} によって生成されました。</entry>
    <entry key="FrameBasedSignalFeatueDefinitionDescription">フレームベースの {0} が、信号ラベラー {1} によって生成されました。</entry>
    <entry key="FeatueExtractionImportErrorDialogTitle">特徴抽出</entry>
    <entry key="FeatueExtractionImportSampeRateMisMatch">データセットに異なるサンプル レートの信号が含まれています。特徴抽出では、サンプル レートが同じである必要があります。データセットから一部の信号を削除することを検討してください。</entry>
    <entry key="FeatueExtractionImportComplexSignal">データセットに複素信号が含まれていますが、これは特徴抽出ではサポートされていません。データセットから複素信号を削除してください。</entry>
    <entry key="EmptyFeatureDefNameText">特徴名は有効な MATLAB 変数名である必要があります。</entry>
    <entry key="DuplicateFeatureDefNameText">新規および既存の特徴の名前は一意である必要があります。</entry>
    <entry key="ExportFeatureToCLDlgTitle">特徴を分類学習器にエクスポート</entry>
    <entry key="ExportFeatureTableDlgTitle">特徴をワークスペースにエクスポート</entry>
    <entry key="ExportFeatureTableHeaderLabel">ラベル</entry>
    <entry key="SelectResponseLabel">応答ラベルの選択</entry>
    <entry key="SelectFeatureLabel">特徴ラベルの選択</entry>
    <entry key="FramePolicyLabel">フレーム ポリシー</entry>
    <entry key="FrameSizeLabel">フレーム サイズ ({0}):</entry>
    <entry key="FrameRateLabel">フレーム レート ({0}):</entry>
    <entry key="FrameOverLapLengthLabel">フレームのオーバーラップの長さ ({0}):</entry>
    <entry key="ExportFeatureToWorkspaceDialogNameLabel">名前</entry>
    <entry key="ExportFeatureToWorkspaceDialogOutputAsLabel">出力形式: </entry>
    <entry key="FeatureOutputAsMatrixLabel">行列</entry>
    <entry key="FeatureOutputAsTableLabel">table</entry>
    <entry key="FramePolicyMisMatchError">特徴ラベルはフレーム ポリシーが同じである必要があります。選択を変更してください。</entry>
    <entry key="MultiSignalInSpectrogram">複数の信号のスペクトログラムをプロットすることはできません。スペクトログラム表示をオフにしてください。</entry>
    <entry key="ColoringTypeHeading">ラベルと信号の配色:   </entry>
    <entry key="DifferentColorsOptionLabel">異なる色を使用</entry>
    <entry key="SameColorsOptionLabel">同じ色を使用</entry>
    <entry key="SameColoringAcrossMembersColoringOptionLabel">メンバー全体で同じ色を使用</entry>
    <entry key="DifferentColorsOptionSummary">信号とラベルに異なる色を使用します</entry>
    <entry key="SameColorsOptionSummary">信号とラベルに同じ色を使用します</entry>
    <entry key="SameColoringAcrossMembersColoringOptionSummary">複数信号メンバーの信号には同じ色を使用しますが、異なったラベルの色を使用します</entry>
    <entry key="LongWindowWarningMessage">一部の信号は、2^(floor(log2(L)) + 3) を超えるウィンドウ長を使用してスペクトルが計算されたため、強度レベルが予想より小さくなっています。ここで、L は信号長です。</entry>
    <entry key="DeleteButton">削除</entry>
    <entry key="KeepButton">保持</entry>
    <entry key="DeleteTFLabelsDialogTitle">時間-周波数ラベルの削除</entry>
    <entry key="DeleteTFLabelsDialogSpectrogramMessage">スペクトログラムのパラメーターのアンロックおよび変更により、既存の時間-周波数ラベルが非互換になる可能性があります。</entry>
    <entry key="DeleteTFLabelsDialogQuestion">現在のラベルの定義について、既存の時間-周波数ラベルをすべて削除しますか?</entry>
    <entry key="ExportDatasetToFilesDialogTitle">データ セット ファイルの作成</entry>
    <entry key="ExportDatasetToFilesDialogDescription">ファイルは、メンバー名から派生したファイル名を使用してメンバーごとに作成されます</entry>
    <entry key="ExportDatasetToFilesDialogFolderLabel">フォルダー</entry>
    <entry key="ExportDatasetToFilesDialogFolderPlaceholder">現在のパス</entry>
    <entry key="ExportDatasetToFilesDialogLabelLabel">ラベル</entry>
    <entry key="ExportDatasetToFilesDialogContentsLabel">データ セットの内容</entry>
    <entry key="ExportDatasetToFilesDialogMemberNameLabel">メンバー名</entry>
    <entry key="ExportDatasetToFilesDialogSignalLabel">信号</entry>
    <entry key="ExportDatasetToFilesDialogLabelsLabel">ラベル</entry>
    <entry key="ExportDatasetToFilesDialogLimitFormatLabel">ラベル範囲の形式</entry>
    <entry key="ExportDatasetToFilesDialogStandardLimitLabel">[min x, max x, min y, max y]</entry>
    <entry key="ExportDatasetToFilesDialogObjectDetectionLimitLabel">[x, y, w, h] (オブジェクトの検出に最適)</entry>
    <entry key="ExportDatasetToFilesDialogSemanticSegmentationLimitLabel">マスク (セマンティック セグメンテーションに最適)</entry>
    <entry key="ExportDatasetToFilesDialogBothLimitLabel">両方</entry>
    <entry key="ExportDatasetToFilesDialogTimeFrequencyMapLabel">時間-周波数マップ</entry>
    <entry key="ExportDatasetToFilesDialogTimeFrequencyOptionsLabel">時間-周波数オプション</entry>
    <entry key="ExportDatasetToFilesDialogFormatSpectrogramLabel">スペクトログラム</entry>
    <entry key="ExportDatasetToFilesDialogFormatImageLabel">イメージ (RGB)</entry>
    <entry key="ExportDatasetToFilesDialogFormatWidthLabel">幅</entry>
    <entry key="ExportDatasetToFilesDialogFormatHeightLabel">高さ</entry>
    <entry key="ExportDatasetToFilesDialogGenerateScriptText">MATLAB 関数の生成</entry>
    <entry key="ExportDatasetToFilesDialogGetFolderDialogTitle">保存先フォルダーの選択</entry>
    <entry key="ExportDatasetToFilesDialogErrorDialogTitle">データ セット ファイルの作成エラー</entry>
    <entry key="AddSpectrogramTFLabelDefinitionAlertDialogTitle">スペクトログラム パラメーターがロックされます</entry>
    <entry key="AddSpectrogramTFLabelDefinitionAlertDialogMessage">時間-周波数のラベル付けのためにスペクトログラム パラメーターをロックする必要がある時間-周波数ラベルの定義が追加されました。&lt;br \&gt;&lt;br \&gt;スペクトログラム パラメーターのロックを解除して変更すると、既存のラベルが非互換になる可能性があります。</entry>
    <entry key="MatFileNameExtPlaceholder">.mat</entry>
    <entry key="ValidFileExtensions">.mat</entry>
    <entry key="ImportToAppError">Internal: Import to app error.</entry>
  </message>
</rsccat>
