<?xml version="1.0" encoding="UTF-8"?>
<!--Copyright 2024 The MathWorks, Inc.-->

<rsccat xmlns:xsi="http://www.w3.org/2001/XMLSchema-instance" version="1.0" locale="ja_JP" product="rptgen" xsi:noNamespaceSchemaLocation="../../resources/schema/msgcat.xsd">
  <message>
    <entry key="nameText">クラス ループ</entry>
    <entry key="noClassesMsg">コンテキストなし、レポートするクラスなし</entry>
    <entry key="allClassLabel">現在のパッケージ内のすべてのクラス</entry>
    <entry key="selectClassLabel">クラスの選択</entry>
    <entry key="currentClassLabel">現在のクラス</entry>
    <entry key="loopEnabledLabel">ループ</entry>
    <entry key="autoLabel">自動</entry>
    <entry key="autoFromContextLabel">自動 (コンテキストから)</entry>
    <entry key="customClassListLabel">クラスのカスタムリスト</entry>
    <entry key="classhandle">現在の {0} のクラスハンドル</entry>
  </message>
</rsccat>
