<?xml version="1.0" encoding="UTF-8" ?>
<!-- Copyright 2016-2022 The MathWorks, Inc. -->
<rsccat version="1.0" locale="en_US" product="hwsetup" xmlns:xsi="http://www.w3.org/2001/XMLSchema-instance" xsi:noNamespaceSchemaLocation="../../schema/msgcat.xsd">
    <message>
        <entry key="DefaultWindowTitle">Hardware Setup</entry>
        <entry key="InvalidParent">The parent of a widget should be of type {0} or {1}</entry>
        <entry key="WindowOutOfRange">Window out of screen range</entry>
        <entry key="InvalidTag">The Tag property should be a character string of alphabetical letters, digits and underscores, with length less than or equal to namelengthmax, the first character an alphabetical letter and the name not a keyword</entry>
        <entry key="UnableToChangeParent">The parent for the widget cannot be changed</entry>
        <entry key="WidgetClassDoesNotExist">The class {0} does not exist, unable to create {1}</entry>
        <entry key="WidgetCreatingError">Unable to create widget {0} from parent {1}. Error: {2}</entry>
        <entry key="HWSetupError">Hardware Setup Error</entry>
        <entry key="MLError">MATLAB Error</entry>
        <entry key="Widget">widget</entry>
        <entry key="InvalidDataType"> {0} should be specified as {1}</entry>
        <entry key="IncorrectSize"> Incorrect size for {0}, {1}</entry>
        <entry key="EditTextSection1Header">About Your Selection</entry>
        <entry key="EditTextSection2Header">What to Consider</entry>
        <entry key="EntityDoesNotExist"> {0} does not exist</entry>
        <entry key="Download">Download</entry>
        <entry key="HWSetupTerminated">Hardware Setup Terminated, please try again.</entry>
        
        <!-- BusyOverlay widget strings -->
        <entry key="BusyOverlayPositionReadOnly">The Position property for matlab.hwmgr.internal.hwsetup.BusyOverlay widget is read-only.</entry>
        <entry key="BusyOverlayText">Please wait...</entry>
        
        <!-- HelpText widget strings -->
        <entry key="HelpTextAboutSelectionHeader">About Your Selection</entry>
        <entry key="HelpTextWhatToConsiderHeader">What to Consider</entry>
        
        <!-- HTML strings -->
        <entry key="HTMLHeaderStyle"><![CDATA[<span style="color:blue; font-weight:bold;">]]>{0}<![CDATA[</span>]]></entry>
        <entry key="HTMLErrorStyle"><![CDATA[<span style="color:red; font-weight:bold;">]]>{0}<![CDATA[</span>]]></entry>
        <entry key="HTMLWarningStyle"><![CDATA[<span style="color:orange; font-weight:bold;">]]>{0}<![CDATA[</span>]]></entry>
    </message>
</rsccat>

