<?xml version="1.0"?>
<!-- Copyright 2011 The MathWorks, Inc. -->
<rsccat version="1.0" locale="en_US" product="vision">
  <message>
    <entry key="invalidImageType">
      extractFreak expected its first input to be of uint8 type.
    </entry>
    <entry key="invalidParams">
      extractFreak expected its third input to be a 1-by-1 structure.
    </entry>
    <entry key="invalidNumFieldsInParamsStruct">
      Invalid number of fields in the extractor parameters structure.
    </entry>
    <entry key="invalidStructFieldClassInDoubleParams">
      nbOctave, patternScale fields of parameters structure must be double.
    </entry>
    <entry key="invalidStructFieldClassInLogicalParams">
      orientationNormalized, scaleNormalized fields of parameters structure must be double.
    </entry>
    <entry key="paramFieldMissing">
      FREAK parameters structure must have {0} field.
    </entry>
    <entry key="codegenForFREAKNotSupported">
      Code generation for FREAK features is not supported.
    </entry>
  </message>
</rsccat>
