<?xml version="1.0" encoding="UTF-8"?>
<!--Copyright 2025 The MathWorks, Inc.-->

<rsccat xmlns:xsi="http://www.w3.org/2001/XMLSchema-instance" version="1.0" locale="ko_KR" product="EMLRT" xsi:noNamespaceSchemaLocation="../../resources/schema/msgcat.xsd">
  <message>
    <entry key="MATLABCommandFailed">MATLAB 명령 ''{0}''이(가) 실패했습니다.</entry>
    <entry key="MATLABCommandFailedWithMsg">MATLAB 명령 ''{0}''이(가) 실패했습니다. {1}.</entry>
    <entry key="MATLABCommandFailedWithMsgAndID">MATLAB 명령 ''{0}''이(가) 실패했습니다. ({1}) {2}</entry>
    <entry key="MATLABCallInsideParallelThread">Call to MATLAB command inside parallel thread.</entry>
    <entry key="MATLABDebugQuit">MEX가 dbquit를 시작했습니다</entry>
    <entry key="MATLABExprIsNotCorrectSize">표현식 ''{0}''의 크기가 잘못됨: [{1}]이어야 하는데 [{2}](으)로 되어 있습니다.</entry>
    <entry key="MATLABExprIsNotCorrectClass">표현식 ''{0}''의 클래스가 잘못됨: ''{1}''이어야 하는데 ''{2}''(으)로 되어 있습니다.</entry>
    <entry key="MATLABExprIsNotCorrectNumFields">표현식 ''{0}''의 필드 개수가 잘못됨: {1,number,integer}이어야 하는데 {2,number,integer}(으)로 되어 있습니다.</entry>
    <entry key="MATLABExprIsNotCorrectFieldName">MATLAB expression ''{0}'' field ''{1}'' is not field index {2,number,integer} of struct.</entry>
    <entry key="MATLABExprIsNotCorrectComplexness">MATLAB expression ''{0}'' is not of the correct complexness.</entry>
    <entry key="MATLABExprIsNotCorrectSparseness">MATLAB expression ''{0}'' is not of the correct sparseness.</entry>
    <entry key="MATLABExprIsNotCorrectNumerictype">Incorrect numerictype in expression ''{0}''.</entry>
    <entry key="MATLABExprIsNotCorrectFimath">Incorrect fimath in expression ''{0}''.</entry>
    <entry key="MATLABExprIsNotCorrectEnumClass">MATLAB 표현식 ''{0}''이(가) 알려진 MATLAB 열거형 클래스가 아닙니다.</entry>
    <entry key="ClassObjectCorruption">클래스 ''{0}''의 객체가 손상되었습니다.</entry>
    <entry key="MATLABExprIsNotCorrectEnumType">MATLAB 표현식 ''{0}''에 기본 유형 ''{1}''이(가) 있습니다. 이는 ''int32'' 또는 ''Simulink.IntEnumType''에서 상속해야 합니다.</entry>
    <entry key="MATLABExprIsNotCorrectEnumDef">MATLAB expression ''{0}'' has an inconsistent enumeration definition. The generated function expected {1}.{2}({3,number,integer}), but current definition is {4}.{5}({6,number,integer}).</entry>
    <entry key="MATLABExprIsNotCorrectEnumDefSize">MATLAB expression ''{0}'' has an inconsistent enumeration definition; ''{1}'' has {2,number,integer} enumeration elements, but the generated function expected {3,number,integer} elements.</entry>
    <entry key="MATLABExprIsNotCorrectValue">MATLAB 표현식 ''{0}''에 예상 값이 없습니다.</entry>
    <entry key="MATLABGenericEMLRTError">MATLAB EMLRT 호출에 실패했습니다.</entry>
    <entry key="MATLABIncorrectClass">잘못된 클래스가 발견됨: ''{0}''이어야 하는데 ''{1}''(으)로 되어 있습니다.</entry>
    <entry key="MATLABNonEmptyCellWithUnassignedBase">MATLAB 표현식 ''{0}''은(는) 할당되지 않은 요소 유형을 가진, 비어 있지 않은 동종 셀형 배열입니다. 할당되지 않은 요소 유형을 가진 동종 셀형 배열은 비어 있어야 합니다.</entry>
    <entry key="MATLABSourceModified">{0} MEX 파일이 프로파일링을 위해 계측되었습니다. 그러나 MEX 파일에 대한 MATLAB 소스 파일이 수정되었거나 사용할 수 있는 MATLAB 경로에 없습니다. MEX 파일에 대한 프로파일러 결과가 없습니다.</entry>
    <entry key="UserInterrupt">중단되었습니다.</entry>
    <entry key="MCOSPropertyInitialValueUnsupportedType">속성 ''{0}''에 지원되지 않는 유형의 초기값이 있습니다.</entry>
    <entry key="OutOfBoundEmptyNamed">인덱스가 행렬의 차원을 초과합니다. 배열 ''{0}''이(가) 비어 있으므로 유효한 인덱스가 없습니다.</entry>
    <entry key="OutOfBoundEmptyNamedLhs">Index exceeds matrix dimensions. The array ''{0}'' is empty and therefore has no valid indices. Code generation does not support growing arrays via indexing except by using end+1.</entry>
    <entry key="OutOfBoundEmpty">Index exceeds matrix dimensions. The array is empty and therefore has no valid indices.</entry>
    <entry key="OutOfBoundEmptyLhs">인덱스가 행렬의 차원을 초과합니다. 배열이 비어 있으므로 유효한 인덱스가 없습니다. 코드 생성 시, end+1을 사용하는 경우를 제외하고는 인덱싱을 통해 배열을 확장하는 것은 지원되지 않습니다.</entry>
    <entry key="OutOfBoundRangeNamed">인덱스가 배열 차원을 초과합니다. 인덱스 값 {0,number,integer}이(가) 배열 ''{3}''의 유효한 범위 [{1,number,integer}-{2,number,integer}]을(를) 초과합니다.</entry>
    <entry key="OutOfBoundRangeNamedLhs">인덱스가 배열 차원을 초과합니다. 인덱스 값 {0,number,integer}이(가) 배열 ''{3}''의 유효한 범위 [{1,number,integer}-{2,number,integer}]을(를) 초과합니다. 코드 생성 시, end+1을 사용하는 경우를 제외하고는 인덱싱을 통해 배열을 확장하는 것은 지원되지 않습니다.</entry>
    <entry key="OutOfBoundRange">Index exceeds array dimensions. Index value {0,number,integer} exceeds valid range [{1,number,integer}-{2,number,integer}].</entry>
    <entry key="OutOfBoundRangeLhs">Index exceeds array dimensions. Index value {0,number,integer} exceeds valid range [{1,number,integer}-{2,number,integer}]. Code generation does not support growing arrays via indexing except by using end+1.</entry>
    <entry key="OutOfDesignRange">Value {0} is outside of specified design range [{1} to {2}].</entry>
    <entry key="OutOfTargetRangeTruncated">''{3}''의 타깃 유형 범위 {1,number,integer}-{2,number,integer}(으)로 변환하는 동안 범위를 벗어난 값 {0,number,integer}이(가) 잘렸습니다.</entry>
    <entry key="OutOfShiftRangeTruncated">Shifting by {0,number,integer} bits is not supported; truncating result value to 0.</entry>
    <entry key="ValueIsNonInteger">C의 ''int''형으로 표현 가능한 값이어야 하는데 대신 {0}이(가) 있습니다.</entry>
    <entry key="ValueIsNaN">값은 NaN입니다.\n메모리 손상을 방지하기 위해 종료합니다.</entry>
    <entry key="ValueIsNotGEZero">Value {0} is not greater than or equal to zero.\nExiting to prevent memory corruption.</entry>
    <entry key="DivisionByZero">0으로 나누기가 감지되었습니다.\n0으로 나누기로 인해 조기 종료되었습니다.</entry>
    <entry key="IntegerOverflow">정수 오버플로가 감지되었습니다.\n정수 오버플로로 인해 조기 종료되었습니다.</entry>
    <entry key="ForLoopVector">Cannot determine the exact number of iterations for a loop with range {0}:{1}:{2}.</entry>
    <entry key="SizesMismatch">Sizes mismatch: {0,number,integer} ~= {1,number,integer}.</entry>
    <entry key="SizesMismatchND">Sizes mismatch: {0} ~= {1}.</entry>
    <entry key="SizesMismatchOnDim">Size mismatch error on dimension {0,number,integer}: expected {1,number,integer}, but actual size is {2,number,integer}.</entry>
    <entry key="SizesNotImpxCompatibleOnDim">Size mismatch error on dimension {0,number,integer}: expected {1,number,integer} or a singleton, but actual size is {2,number,integer}.</entry>
    <entry key="SizesOverflowOnDim">Size overflow error on dimension {0,number,integer}: upper bound is {1,number,integer}, but actual size is {2,number,integer}.</entry>
    <entry key="SubsAssignDimsMismatch">첨자를 사용한 대입식의 차원이 일치하지 않음: {0} ~= {1}.</entry>
    <entry key="BadStructFieldNameIndex">MATLAB 구조체에 인덱스 {1,number,integer}이(가) 있는 ''{0}''이라는 이름의 필드가 없습니다.</entry>
    <entry key="BadClassPropertyName">MATLAB class ''{0}'' does not have a property named ''{1}''.</entry>
    <entry key="BadClassPropertyCount">MATLAB 클래스 ''{0}''의 속성 개수가 {1, number, integer}이(가) 아닙니다.</entry>
    <entry key="FiConstructorError">FI 생성자가 메시지 ''{0}''을(를) 보고했습니다.</entry>
    <entry key="MatrixMatrix">행렬(matrix) 첨자가 컴파일된 가정과 형태가 다른 벡터(vector) 첨자입니다.</entry>
    <entry key="VectorVector">벡터(vector) 첨자가 컴파일된 가정과 형태가 다른 스칼라(vector) 첨자입니다.</entry>
    <entry key="GrowColumnWithScalarRuntime">end+1 인덱싱을 사용하여 첫 번째 차원 방향으로 스칼라 확장을 시도했습니다. 이 동작은 두 번째 차원 방향으로 스칼라를 확장시키는 MATLAB 실행과 다릅니다.</entry>
    <entry key="FunctionNotInitialized">이 함수는 초기화되지 않았습니다.</entry>
    <entry key="MexFunctionCorrupted">이 MEX 함수는 손상되었습니다.</entry>
    <entry key="MexFunctionNeedsLicense">라이선스 "{0}"을(를) 가져오지 못했습니다.</entry>
    <entry key="MexFunctionNeedsFxpLicense">This function requires the Fixed-Point Designer license.</entry>
    <entry key="MexFunctionRTLLoadFailed">런타임 라이브러리를 불러오지 못했습니다. 오류 코드 = {0,number,integer}.</entry>
    <entry key="FxpLoggingNotSupported">이 함수는 고정소수점 기록을 지원하지 않습니다. 고정소수점 기본 설정(fipref)의 LoggingMode 설정을 무시합니다.</entry>
    <entry key="FiprefCallFailed">FIPREF 함수는 사용할 수 없습니다. Fixed-Point Designer가 설치되어 있는지 확인하십시오.</entry>
    <entry key="DifferentFimath">이 함수는 현재 디폴트 값과 다른 디폴트 fimath로 생성되었습니다.</entry>
    <entry key="DifferentDTOMode">This function was generated with different Data Type Override mode: {0} ~= {1}</entry>
    <entry key="ConstantInputValueMismatch">Constant function parameter ''{0}'' has a different run-time value than the compile-time value.</entry>
    <entry key="ConstantGlobalVariableValueMismatch">Constant global variable ''{0}'' has a different run-time value than the compile-time value.</entry>
    <entry key="NoRunTimeStackMemory">메모리가 부족하여 런타임 스택을 유지할 수 없습니다.</entry>
    <entry key="RunTimeStackPopEmpty">런타임 스택 오류: 빈 스택에서 꺼냅니다(pop).</entry>
    <entry key="RunTimeStackPopMismatch">런타임 스택 오류: 빈 불일치에서 꺼냅니다(pop).</entry>
    <entry key="RunTimeErrorOccurredNoExtrinsic">Detected a run-time error, but cannot report the details because the extrinsic function call setting is disabled. To see the error message, enable extrinsic function calls. In a project, on the Speed tab, select the Keep extrinsic calls check box. In a code configuration object, set the ''ExtrinsicCalls'' property to true.</entry>
    <entry key="RunTimeErrorOccurredStandalone">Detected a run-time error from a call to the function ASSERT or ERROR, but unable to report the details in standalone code. To see the error message, generate and execute a MEX function.</entry>
    <entry key="NoHeapReferenceMemory">메모리가 부족하여 힙 참조 스택을 유지할 수 없습니다.</entry>
    <entry key="HeapOverflow">Not enough memory to support dynamic memory allocation for variable-sized arrays.</entry>
    <entry key="NumelOverflow">intmax()보다 더 큰 개수의 요소를 갖는 행렬로 확장할 수 없습니다.</entry>
    <entry key="UnsupportedNumericType">내부 오류: 지원되지 않는 숫자형입니다.</entry>
    <entry key="UnsupportedArrayType">내부 오류: ''{0}''은(는) 지원되지 않는 배열 유형 입니다.</entry>
    <entry key="HeapMemRecordsLeaveSync">내부 오류: 힙 메모리 레코드가 동기화되지 않았습니다.</entry>
    <entry key="WarningInsideParallelRegion">병렬 영역 내부에 경보가 발생하였으며 표시가 차단되었습니다.</entry>
    <entry key="ParallelNumThreads">최대 스레드 개수는 0, 양의 정수, Inf 중 하나여야 합니다.</entry>
    <entry key="BadMessageID">알 수 없는 런타임 오류: {0}</entry>
    <entry key="UnknownRuntimeException">알 수 없는 런타임 예외입니다.</entry>
    <entry key="UnknownLocation">알 수 없는 위치</entry>
    <entry key="WrongNumberOfInputs">진입점 ''{1}''에 {0,number,integer} 입력값이 필요합니다.</entry>
    <entry key="WrongNumberOfInputsFAVDefaultValues">{0,number,integer} input(s) required for entry-point ''{1}''. The number of provided arguments must match the arguments provided during input type specification when code was generated.</entry>
    <entry key="TooManyOutputArguments">Too many output arguments for entry-point ''{0}''.</entry>
    <entry key="TooFewInputsConstants">You did not provide all the required input arguments for ''{0}''. Check the function signature for ''{1}''. Function ''{2}'' takes constant inputs; verify that you are providing these to the MEX function.</entry>
    <entry key="TooManyInputsConstants">You provided too many input arguments for ''{0}''. Check the function signature for ''{1}''. The code generation software removed constant inputs from the MEX function signature. To include constant inputs in the MEX function signature, configure your MEX settings to include constant inputs.</entry>
    <entry key="MissingMultipleEntryPointName">
      Entry-point function name not specified.\n
      When calling MEX functions that have multiple entry-point functions,\n
      the first argument must be the name of the entry-point function to call.\n
      Follow this argument with the arguments that the named entry-point\n
      function requires.\n
    </entry>
    <entry key="InvalidMultipleEntryPointName">
      Name ''{0}'' is not a recognized entry-point function name.\n
      When calling MEX functions that have multiple entry-point functions,\n
      the first argument must be the name of the entry-point function to call.\n
      Follow this argument with the arguments that the named entry-point\n
      function requires.\n
    </entry>
    <entry key="NontunableHandleProp">조정 불가형 속성의 값은 변경할 수 없습니다.</entry>
    <entry key="RepeatedExprWithDifferentResultsInColonIndexing">인덱싱 표현식의 크기를 예측할 수 없습니다. 표현식 내에서 함수 호출에 대해 지정되지 않은 실행 순서에 따라 달라집니다. 실행 순서를 수정하려면 호출을 별도의 명령문에 배치하십시오.</entry>
    <entry key="DimensionSizeTooLarge">The size of dimension {0,number,integer} of ''{1}'' is specified as {2,number,integer} which is larger than the code generation limit of {3,number,integer}.</entry>
    <entry key="ErrorInFcnAtLine">{0}에서 오류 발생(라인 {1,number,integer})</entry>
    <entry key="ForLoopZeroStride">스트라이드가 없는 벡터 표현식은 지원되지 않습니다.</entry>
    <entry key="ForLoopSingleNumelCauseRoundoff">길이가 {0,number,integer}인 루프 범위는 ''single'' 유형의 인덱스 변수로 정확히 나타낼 수 없습니다. 인덱스 값을 반올림하면 예기치 않은 결과가 발생할 수 있습니다. double형 또는 정수를 인덱스 변수로 사용하십시오.</entry>
    <entry key="CannotCreateObjectOfClass">클래스 ''{0}''의 객체를 생성할 수 없음: {1}</entry>
    <entry key="UnableToFindSymbolInLibrary">공유 오브젝트 파일 ''{1}''에서 기호 ''{0}''을(를) 찾을 수 없음</entry>
    <entry key="ProfilingNoCoder">MATLAB Coder를 설치하지 않으면 MATLAB Coder가 생성한 MEX의 프로파일링이 지원되지 않습니다.</entry>
    <entry key="InitializeGPULibraryError">선택한 GPU 장치에서 MATLAB GPU 라이브러리를 초기화하는 중에 오류가 발생했습니다.</entry>
    <entry key="WarningFromMEXDestructor">다음과 같은 이유로 MEX 함수 {0}이(가) 비정상적으로 종료되었습니다: {1}.</entry>
    <entry key="InvalidCharacterEncodingMEXInit">Unable to initialize the MEX because the MATLAB code generation character encoding ''{0}'' is invalid.</entry>
    <entry key="EncodingSizeConsistencyError">Conversion of string ''{0}'' from UTF-16 to MATLAB code generation character encoding (''{1}'') changes the number of characters. This behavior is not supported for code generation.</entry>
    <entry key="DecodingSizeConsistencyError">Conversion of string from the MATLAB code generation character encoding (''{0}'') to UTF-16 changes the number of characters. This behavior is not supported for code generation.</entry>
    <entry key="EncodingConversionError">Unable to convert string ''{0}'' from UTF-16 to the MATLAB code generation character encoding ''{1}''.</entry>
    <entry key="DecodingConversionError">Unable to convert string from the MATLAB code generation character encoding ''{0}'' to UTF-16.</entry>
    <entry key="NonAsciiSprintf">Arguments to sprintf contain non-ASCII characters. Non-ASCII characters are not supported as arguments to sprintf for code generation.</entry>
    <entry key="UnboundClassEntryPoint">Unable to execute action on class entry point ''{0}'' because it is no longer bound to a MEX.</entry>
    <entry key="ClassEntryPointNotScalar">클래스 진입점에 대한 예상 스칼라 값입니다.</entry>
    <entry key="DeletedEntryPointClass">클래스 진입점 인수는 삭제된 핸들일 수 없습니다.</entry>
    <entry key="LoadLibraryError">{0}</entry>
  </message>
</rsccat>
