<?xml version="1.0" encoding="UTF-8"?>
<!--Copyright 2024 The MathWorks, Inc.-->

<rsccat xmlns:xsi="http://www.w3.org/2001/XMLSchema-instance" version="1.0" locale="ja_JP" product="vision" xsi:noNamespaceSchemaLocation="../../resources/schema/msgcat.xsd">
  <message>
    <entry key="droppingAttributeData">groundTruth オブジェクトには、属性またはサブラベル データが含まれます。これらは出力テーブルには含まれません。</entry>
    <entry key="emptyObjectDetectorData">入力の groundTruth オブジェクトはオブジェクト検出器の有効な学習データを含みません。</entry>
    <entry key="tableOutputNotSupported">すべての入力 groundTruth データ ソースが同じカスタム読み取り関数をもつイメージ データストアの場合、学習データをテーブルに返すことはできません。代わりに 2 出力の構文 [imds, blds] = objectDetectorTrainingData(gTruth) を使用してください。</entry>
    <entry key="labelTypeNotSupported">Invalid 'LabelType' value. 'LabelType' value must be labelType.Rectangle or labelType.ProjectedCuboid.</entry>
    <entry key="emptyAttributeSublabelData">入力のグラウンド トゥルース データに属性またはサブラベルが含まれていません。</entry>
  </message>
</rsccat>
