<?xml version="1.0" encoding="UTF-8"?>
<!--Copyright 2024 The MathWorks, Inc.-->

<rsccat xmlns:xsi="http://www.w3.org/2001/XMLSchema-instance" version="1.0" locale="ko_KR" product="images" xsi:noNamespaceSchemaLocation="../../resources/schema/msgcat.xsd">
  <message>
    <entry key="appName">영상 브라우저</entry>
    <entry key="unrecognizedInput">입력값이 폴더나 영상 datastore 객체가 아님</entry>
    <entry key="Browse">찾아보기</entry>
    <entry key="File">파일</entry>
    <entry key="new">새로 만들기</entry>
    <entry key="newSessionToolTip">현재 내용을 지우고 재초기화하여 새 데이터를 불러옵니다</entry>
    <entry key="Add">추가</entry>
    <entry key="Thumbnails">축소판</entry>
    <entry key="Visualization">시각화</entry>
    <entry key="Analysis">분석</entry>
    <entry key="Preview">미리보기</entry>
    <entry key="images">영상</entry>
    <entry key="Folder">영상 폴더</entry>
    <entry key="FolderWithSub">폴더(하위 폴더 포함)</entry>
    <entry key="IMDS">작업 공간의 영상 데이터저장소</entry>
    <entry key="LoadToolTip">영상을 앱에 불러오려면 클릭하십시오.</entry>
    <entry key="SelectFolder">영상이 있는 폴더 선택</entry>
    <entry key="AddToolTip">영상을 앱에 추가하려면 클릭합니다</entry>
    <entry key="ThumbnailSize">축소판 크기</entry>
    <entry key="ThumbnailSizeTooltip">슬라이더를 움직여 축소판 크기를 변경합니다.</entry>
    <entry key="PreviewTooltip">미리보기 창을 전환합니다.</entry>
    <entry key="exportAll">모두</entry>
    <entry key="exportSelected">선택 항목</entry>
    <entry key="exportTooltip">imageDatastore로 내보냅니다</entry>
    <entry key="exportVariableLabel">이미지 데이터저장소</entry>
    <entry key="loadingFolder">{0}에서 영상을 불러오는 중</entry>
    <entry key="loadedN">{0}개 영상을 불러왔습니다.</entry>
    <entry key="addedN">{0}개의 영상이 추가되었습니다.</entry>
    <entry key="selectedN">{0}개 영상을 선택했습니다.</entry>
    <entry key="clearContent">현재 불러온 영상 축소판이 지워집니다. 계속하시겠습니까?</entry>
    <entry key="clearContentTitle">축소판 지우기</entry>
    <entry key="importImageDataStore">작업 공간에서 영상 데이터저장소 선택</entry>
    <entry key="unableToLoad">{0}에서 영상을 불러올 수 없습니다.</entry>
    <entry key="unableToLoadTitle">영상을 불러올 수 없음</entry>
    <entry key="removeFromBrowser">브라우저에서 제거</entry>
    <entry key="noImagesInImdsFoundDetail">데이터저장소에서 영상을 찾을 수 없음: {0}</entry>
    <entry key="lrButtonToolTips">선택한 영상들을 스크롤합니다.</entry>
    <entry key="noLabelsWarningTitle">레이블은 지원되지 않습니다.</entry>
    <entry key="noLabelsWarning">이 imageDatastore에는 Labels 속성이 설정되어 있습니다. Labels 속성이 앱에서 무시됩니다.</entry>
    <entry key="copiedToClipBoard">파일 이름이 클립보드에 복사되었습니다.</entry>
    <entry key="size">크기:</entry>
    <entry key="class">클래스:</entry>
    <entry key="clickLoad">영상을 가져오려면 [불러오기] 클릭...</entry>
    <entry key="exportAllTooltip">모든 영상을 imageDatastore 객체로 내보냅니다</entry>
    <entry key="Load">불러오기</entry>
    <entry key="LoadFolder">영상 폴더 불러오기</entry>
    <entry key="LoadFolderWithSub">하위 폴더를 포함하여 폴더 불러오기</entry>
    <entry key="LoadIMDS">작업 공간에서 영상 데이터저장소 불러오기</entry>
    <entry key="noimds">작업 공간에서 영상 데이터저장소 변수를 찾을 수 없습니다. 영상 데이터저장소를 만드는 방법을 알아보려면 doc imageDatastore를 입력하십시오.</entry>
    <entry key="noimdsTitle">영상 데이터저장소를 찾을 수 없음</entry>
    <entry key="various">다양</entry>
  </message>
</rsccat>
