<?xml version="1.0" encoding="UTF-8"?>
<!--Copyright 2024 The MathWorks, Inc.-->

<rsccat xmlns:xsi="http://www.w3.org/2001/XMLSchema-instance" version="1.0" locale="ja_JP" product="images" xsi:noNamespaceSchemaLocation="../../resources/schema/msgcat.xsd">
  <message>
    <entry key="mustSpecifyImage">構文があいまいです。関連付けられている Axes には複数のイメージが含まれています。イメージ ハンドルを入力引数として指定し、あいまいさをなくしてください。</entry>
    <entry key="noImage">createMask にはイメージを含む現在の Figure が必要です。</entry>
    <entry key="invalidImageObj">image オブジェクトは有効でなければなりません。</entry>
    <entry key="invalidParent">ROI の親は有効な axes オブジェクトでなければなりません。</entry>
    <entry key="invalidCreateMaskInput">createMask には 1 つのイメージか、または出力マスクの行数と列数を指定する 2 つの入力引数のいずれかが必要です。</entry>
    <entry key="invalidDrawingAreaInput">入力が無効です。入力は 'auto' または 'unlimited' でなければなりません。</entry>
    <entry key="invalidInteractionInput">入力が無効です。入力は [all]、[translate]、[reshape]、または [none] でなければなりません。</entry>
    <entry key="invalidLimits">DrawingArea の範囲には、非負の幅と高さがなければなりません。</entry>
    <entry key="fixedNaNAspectRatio">AspectRatio が NaN と等しい場合、FixedAspectRatio は true に設定できません。</entry>
    <entry key="incompleteDefinition">ROI は完全には定義されていません。''{0}'' は無視され、対話型の配置が開始されます。</entry>
    <entry key="unusedParameter">''{0}'' は対話型の配置の開始時に設定することはできないため無視されます。ROI が描画された後、または完全に定義された後に、このプロパティを目的の値に設定してください。</entry>
    <entry key="fixAspectRatio">縦横比を固定</entry>
    <entry key="deleteRectangle">四角形の削除</entry>
    <entry key="invalidRectangle">四角形の高さと幅は非負でなければなりません。</entry>
    <entry key="invalidRectangleInteractionInput">四角形 ROI の入力 ''{0}'' が無効です。入力は 'all'、'translate' または 'none' でなければなりません。</entry>
    <entry key="rotationStemInGeographicAxes">Rectangle with rotation stem cannot be children for GeographicAxes.</entry>
    <entry key="deletePolygon">多角形の削除</entry>
    <entry key="addVertex">頂点の追加</entry>
    <entry key="deleteVertex">頂点の削除</entry>
    <entry key="deletePolyline">ポリラインの削除</entry>
    <entry key="deleteFreehand">フリーハンドの削除</entry>
    <entry key="addWaypoint">ウェイポイントの追加</entry>
    <entry key="deleteWaypoint">ウェイポイントの削除</entry>
    <entry key="invalidWaypoints">ウェイポイントは N 行 1 列の logical 配列でなければなりません。ここで、N は ROI Position で定義された点の数です。</entry>
    <entry key="deleteEllipse">楕円の削除</entry>
    <entry key="deleteCircle">円の削除</entry>
    <entry key="deleteLine">ラインの削除</entry>
    <entry key="deletePoint">点の削除</entry>
    <entry key="invalidPointInteractionInput">ポイント ROI の入力 ''{0}'' が無効です。入力は 'all' または 'none' でなければなりません。</entry>
    <entry key="deleteCrosshair">十字形の削除</entry>
    <entry key="invalidCrosshairInteractionInput">十字形 ROI の入力 ''{0}'' が無効です。入力は 'all' または 'none' でなければなりません。</entry>
    <entry key="noimages">イメージ ハンドルが検出されませんでした。</entry>
    <entry key="invalidImage">イメージ ハンドルが無効です。draw メソッドを呼び出す前に Image プロパティを設定してください。</entry>
    <entry key="invalidImageLimits">image オブジェクトの XData プロパティおよび YData プロパティが、親座標軸の XLim プロパティおよび YLim プロパティと矛盾しています。</entry>
    <entry key="parentMismatch">Parent プロパティは、Image プロパティ内の image オブジェクトの親である座標軸と一致しなければなりません。</entry>
    <entry key="drawingCanvasIsReadOnly">DrawingCanvas は読み取り専用プロパティです。</entry>
    <entry key="assistedFreehandInGeographicAxes">AssistedFreehand を GeographicAxes の子にすることはできません。フリーハンドの ROI を GeographicAxes と共に使用してください。</entry>
    <entry key="lockDimensions">次元をロック</entry>
    <entry key="deleteCuboid">直方体を削除</entry>
    <entry key="invalidCuboid">直方体の高さ、幅、および深さは、非負でなければなりません。</entry>
    <entry key="invalidCuboidInteractionInput">直方体 ROI の ''{0}'' は無効な入力です。入力は [all]、[translate]、または [none] でなければなりません。</entry>
    <entry key="cuboidInGeographicAxes">直方体を GeographicAxes の子にすることはできません。</entry>
  </message>
</rsccat>
