<?xml version="1.0" encoding="UTF-8"?>
<!--Copyright 2024 The MathWorks, Inc.-->

<rsccat xmlns:xsi="http://www.w3.org/2001/XMLSchema-instance" version="1.0" locale="zh_CN" product="MATLAB" xsi:noNamespaceSchemaLocation="../../resources/schema/msgcat.xsd">
  <message>
    <entry key="FirstArg">第一个参数必须为数值、逻辑值或字符数组。</entry>
    <entry key="SecondArg">第二个参数必须为实整数标量。</entry>
    <entry key="SecondArgWithSignificant">如果带有 'significant' 标志，第二个输入必须为正数。</entry>
    <entry key="ThirdArg">在有 3 或 5 个输入参数的情况下，第三个输入必须为 'decimals' 或 'significant'。</entry>
    <entry key="DirectionName">参数名称必须为 'TieBreaker'。</entry>
    <entry key="DirectionValue">'TieBreaker' 值必须为 'fromzero'、'tozero'、'even'、'odd'、'plusinf' 或 'minusinf'。</entry>
    <entry key="NonfloatMultipleArgs">第一个参数必须为双精度或单精度值并且有多个输入。</entry>
    <entry key="complexIntegers">ROUND 不支持复整数。 </entry>
  </message>
</rsccat>
