<?xml version="1.0"?>
<!-- Copyright 2021 The MathWorks, Inc. -->
<rsccat version="1.0" locale="en_US" product="polyspace">
  <message>
      <entry key="catalogNotProvided">No catalog id provided.</entry>
      <entry key="catalogDoesNotExist">Message catalog {0} does not exist.</entry>
      <entry key="catalogsDoNotExist" note="when catalog and fallback english catalog don't exist">Message catalogs {0} and {1} do not exist.</entry>
      <entry key="noMessageId">Message id not given in '{0}'.</entry>
      <entry key="noCatalog">Message catalog not given in '{0}'.</entry>
      <entry key="invalidMessageId">Invalid message id '{0}'.</entry>
      <entry key="messageCatalogLoadFailed">Failed to load message catalog '{0}'.</entry>
      <entry key="messageNotFound">Message id '{0}' not found in '{1}'.</entry>
      <entry key="incorrectHoleCount">Incorrect number of arguments for message id {0} expected {1} argument(s) but given {2}.</entry>
  </message>
</rsccat>
