<?xml version="1.0" encoding="UTF-8"?>
<!--Copyright 2024 The MathWorks, Inc.-->

<rsccat xmlns:xsi="http://www.w3.org/2001/XMLSchema-instance" version="1.0" locale="ja_JP" product="MATLAB" xsi:noNamespaceSchemaLocation="../../resources/schema/msgcat.xsd">
  <message>
    <entry key="Delete">削除</entry>
    <entry key="DeleteAll">すべて削除</entry>
    <entry key="ClearWorkspaceTitle">すべての変数を削除</entry>
    <entry key="DeleteSingleVarTitle">変数の削除</entry>
    <entry key="DeleteMultipleVarsTitle">変数の削除</entry>
    <entry key="DeleteSingleFieldTitle">フィールドの削除</entry>
    <entry key="DeleteMultipleFieldsTitle">フィールドの削除</entry>
    <entry key="ClearWorkspaceConfirmation">ワークスペースのすべての変数を削除してもよろしいですか?</entry>
    <entry key="DeleteVariableConfirmation">選択した変数を削除しますか?</entry>
    <entry key="DeleteVariablesConfirmation">選択した変数を削除しますか?</entry>
    <entry key="DeleteFieldConfirmation">選択したフィールドを削除しますか?</entry>
    <entry key="DeleteFieldsConfirmation">選択したフィールドを削除しますか?</entry>
  </message>
</rsccat>
